Workbook

Sheet Verdicts
A1: Step 5 of the review: what the published page says, claim by claim, and what the review supports
A2: The page is the visual essay "Encampment, Self-Settlement and the Recovery of Displaced Households: Syrian Refugees in Jordan" (index.html, with the Spanish version index_espanol.html, which carries the same figures). Each row is one claim of the page, in the order of the page, read against the four earlier steps of the review: step 1 (what the survey measures well), step 2 (whom the sample represents), step 3 (the theory of change) and step 4 (design 1, the shocks family, the decomposition, the four indices and the flexible-estimation check). Abbreviations in the "Where in the review" column: S1 = encampment_variable_audit.xlsx; S2 = encampment_sample_and_benchmarks.xlsx; S3 = encampment_theory_of_change.xlsx; S4 = encampment_design_diagnostics.xlsx (seventh edition); "step 2 profile" = the profile of the two groups behind steps 2 and 3 (script b1_profile.py, aggregate file b1_profile.min.json), cited where a figure sits in that aggregate and is not printed on a sheet; "step 5b" = the descriptive cuts declared in review/brief_5b.md on 21 October 2026 (the composition of reported spending, the rent burden and income after rent, the responses by thirds of the rent burden, the average day by group and sex of the respondent), computed on the author's computer (aggregate file out_c7.json), replicated blind and printed in the technical note (encampment_technical_note.ipynb, Tables 4.4 to 4.6 and 7.10). A count below ten that the page itself prints is masked here in square brackets.
A3: Five verdicts, fixed before the claims were read against the review. Holds: the review confirms the figure and the reading. Holds with new wording: the fact holds and the wording changes for the rules fixed for the review (no effects, the names decided, the lexicon, households as the subject of each sentence, protection of small counts). Revise: the review gives another number or another reading and the claim changes in substance. Not supported: the review contradicts it or the data cannot carry it, so it goes. Not checked: the review did not test it, and the row says what it would take. Two flags beside the verdict: protection (the sentence prints, or lets a reader work out, a count below ten households) and language (a causal verb, a place as the subject, a name not agreed, the word the author avoids, a headline wider than its figure, or a statement that needs its source named). The last column gives the part of the chain of the step 3 workbook that the claim belongs to.
A5: No. | B5: Chapter | C5: Where on the page | D5: What the page says | E5: What the review found | F5: Where in the review | G5: Verdict | H5: Wording proposed for the page | I5: Protection flag | J5: Language flag | K5: Part of the chain
A6: Title, lead and map
A7: 0.1 | B7: 0 | C7: Lead paragraph | D7: The same 391 families described their lives in Syria before the war and in Jordan in 2016; inside Zaatari camp and outside it, Jordan hosted them under two different sets of rules; the page tells what each family lost, what it rebuilt, and why. | E7: The counts hold (257 households interviewed in Zaatari camp, 134 in northern towns). The pre-war module covers resources and traits (income, goods, savings, debts, business, car, pension, vacations, housing, schooling), not the responses, the scales or the shocks, so the page can speak of a pre-war module rather than of the same questionnaire asked twice. "Why" promises causes; the review found no causal design in the data (no instrument, no discontinuity, no cohort structure), so the page can show what goes with living in each place, not what each place did. | F7: S4 How it was done (rows 3 and 4); S1 Variables (the blocks on Syria); S3 How it was done | G7: Holds with new wording | H7: Between June and August 2016, 391 Syrian refugee households were interviewed in Jordan, 257 in Zaatari camp and 134 in northern towns. Each household also described its resources in Syria before the war. The two groups lived under different rules in Jordan, and the page shows what households in each setting lost, what they rebuilt, and what went with each outcome. | J7: causal promise ("why") | K7: 0
A8: 0.2 | B8: 0 | C8: Map caption | D8: Three in four households came from Daraa governorate, just across the border (Daraa city about 12 km from Ramtha); lines are drawn only for origin and destination pairs with at least 5 households (353 of the 380 households with a recorded origin); 11 households did not record an origin. | E8: Daraa origin: 86% in the camp and 64% in the towns, about three in four of the 380 households with a recorded origin. Ramtha lies about 11 km from Daraa in a straight line (Tokmajyan 2021 gives some 10 km). The map rule (pairs of five or more) is the one decided on 21 October 2026. The figure changes: under the coding of origin of the step 2 profile, which the step 2 workbook and the map of the brief use, the lines drawn cover 351 of the 380 households with a recorded origin; the page's figure came from an aggregate of the map computed on 5 October 2026, which coded some places of origin differently (found by the check of coherence of 23 October 2026). The counts printed (351 of 380; 11 without origin) are at or above ten. | F8: S2 Comparison (No. 1, 2 and 24); S3 Checks, section 6 (distances); flows by origin and place of interview under the step 2 coding (map/m1_flujos.py, computed on the author's computer on 23 October 2026) | G8: Revise | H8: The caption with 351 in place of the page's figure. One check remains in the HTML of the page: the hover shows counts by governorate of origin at each destination, and a pair of five to nine households would print a count below ten; the rule agreed for the map (five or more) covers the lines drawn, and the counts shown should follow the same rule, stated on the page, or the ten rule. The brief that replaces the page shows the width class in its hover and prints counts for the two largest flows to the camp only. | I8: hover counts by governorate of origin to be checked in the HTML | K8: 0
A9: 0.3 | B9: 0 | C9: Lead, chapter 1 and methods | D9: Fieldwork took place between May and July 2016. | E9: The two documents of 2016 and 2017 in the folder say June and July 2016; the file holds no interview date (16 records of the raw sheet carry one date, in August 2016); Ramadan ran from 6 June to 5 July 2016. Author's account (21 October 2026): fieldwork ran from June to August 2016, which the dated records of the raw sheet fit. The step 1 finding is to be updated in the next edition of that workbook. | F9: S1 Findings (No. 1 and 2); author's account, 21 October 2026 | G9: Revise | H9: Between June and August 2016 (and, in the methods section, the same months in place of May to July). | K9: 0
A10: Chapter 1. The households
A11: 1.1 | B11: 1 | C11: Chapter 1, opening | D11: 391 households: 257 in the twelve districts of Zaatari camp and 134 in Irbid, Ramtha, Jerash, Zarqa and the towns around them. | E11: Holds: 257 camp households spread over the twelve districts like the REACH count of January 2015; 134 towns households (52 in Irbid, 38 in Ramtha, 24 in Jerash, 10 in Zarqa and fewer than ten in three other places). | F11: S2 Places and districts; S2 Findings (No. 1 and 6) | G11: Holds | H11: No change. The page can add, once, that two thirds of the towns group live in Irbid and Ramtha, the two cities nearest to Daraa, and that the results do not extend to Amman, where a third of all Syrians lived (fewer than ten households in the sample). | K11: 0
A12: 1.2 | B12: 1 | C12: Chapter 1, unit chart | D12: Every household answered the same questionnaire twice over: about its life in Jordan, and about its life in Syria before the war. | E12: Overstated. The Syria module records resources and traits before the war (income, durable goods, savings, debts, loans, business, car, pension, vacations, outings, housing tenure, informal work); the shocks, the eleven responses, the scales, security and assistance were asked for Jordan only. The review uses the Syria answers as pre-war traits for the comparison, not as a second wave. | F12: S1 Variables (blocks on Syria); S3 Theory of change, part 8 (column H); S4 Verdict (sample note) | G12: Revise | H12: Each household also answered a module on its resources in Syria before the war: income, durable goods, savings, debts, business, car, pension and housing. Those answers describe the household before displacement and serve to compare like with like. | K12: 0
A13: 1.3 | B13: 1 | C13: Chapter 1, unit chart | D13: Inside the camp: registration, food vouchers, a caravan and almost no work. Outside: movement, informal work and rent. | E13: "Almost no work" overstates: 36% of camp households name work income among their sources and 39% name a member who works (67% and 64% in the towns). Among comparable households the work-income difference is 24 points (robust). Rent: 87% of towns households rent (median JD 130, Jordanian dinars); fewer than ten camp households do. | F13: S3 Figures; S2 Findings (No. 8); S4 Verdict (income from work) | G13: Revise | H13: Inside the camp: registration, a caravan, the food voucher for nine households in ten, and work income in about one household in three. In the towns: movement, work income in two households of three, and rent for nearly nine in ten. | K13: 1
A14: 1.4 | B14: 1 | C14: Chapter 1, unit chart (routes out of the camp) | D14: The 134 households outside the camp got there in different ways: 49 never entered a camp; 42 left Zaatari with a Jordanian sponsor, the legal route until 2015; [a count] left informally; [a count below ten] left with a permit or did not say. | E14: The page prints a count below ten, and the three other counts let a reader work it out by subtraction. Of the 134 towns households, 84 passed through a camp (71 lived in Zaatari and 13 in Azraq, so "left Zaatari" is not exact), 42 report leaving with a sponsor and most of the rest informally; the other routes have fewer than ten households. Households that left with a sponsor weigh more in the sample than in the UNHCR estimate (27% of exits). The page's 49 that never entered a camp and the review's 84 that passed through one do not partition the 134 the same way (the review's base is the households that report having passed through a camp), so the two figures are not combined. | F14: S2 Comparison (No. 32 and 33); S2 Findings (No. 14); S3 Theory of change, part 0 (column F) | G14: Holds with new wording | H14: Of the 134 households in the towns, 84 passed through a camp and 50 did not. Of those 84, 42 report leaving with a Jordanian sponsor, the legal route until 2015, and the other 42 left informally, by another route, or did not say how. Households that left with a sponsor weigh more in this sample than among all exits from Zaatari. | I14: prints a count below ten; the four counts add to the group total | K14: 0
A15: 1.5 | B15: 1 | C15: Chapter 1, unit chart | D15: How a family left later decided which documents it could hold. | E15: A statement about the rules, not about the survey, and the sources support it: from July 2014 households that left a camp without a sponsor could not obtain the Ministry of Interior card, and the sponsor route was suspended in January 2015 (NRC and IHRC 2016). The survey did not ask about the card. | F15: S3 Literature (NRC and IHRC 2016); S3 Theory of change, part 0 (columns G and H) | G15: Holds with new wording | H15: Under the rules of the time, the route out of a camp decided which documents a household could later hold: those that left without a sponsor after July 2014 could not obtain the Ministry of Interior card (NRC and IHRC 2016). The survey did not ask about the card. | J15: cite the source in the sentence | K15: 0
A16: 1.6 | B16: 1 | C16: Chapter 1, unit chart (registration) | D16: The survey never asked about Ministry of Interior cards. It did ask about UNHCR registration: [a total that fixes a camp count below ten] households were still waiting to be registered, twelve of them outside the camp, most of them recent arrivals or families that never entered a camp; the ring marks them. | E16: The two counts leave a count below ten for the camp by subtraction, the ring marks those households one by one on the chart, and "most of them recent arrivals or families that never entered a camp" cuts the twelve into cells below ten. Twelve towns households and fewer than ten camp households reported being asylum seekers; none reported being unregistered. There is no variation to compare. The sentence under the chart, that no dot is an identifiable household, holds once the ring goes. | F16: S1 Findings (No. 14); S2 Comparison (No. 28); S2 Findings (No. 17) | G16: Holds with new wording | H16: The survey never asked about Ministry of Interior cards. It did ask about UNHCR registration: twelve households in the towns, and fewer than ten in the camp, reported being asylum seekers still awaiting registration; none reported being unregistered. (The ring on the chart goes, and the cut of the twelve by arrival and camp history goes with it.) | I16: camp count below ten by subtraction; the twelve cut into cells below ten; the chart marks them | K16: 0
A17: 1.7 | B17: 1 | C17: Chapter 1, unit chart (who answered) | D17: Women answered 63 percent of the interviews outside the camp and 21 percent inside, the largest difference between the two samples; every subjective answer on the page is read with that in mind. | E17: Holds: a woman answered in 63% of towns households and 21% of camp households (standardized difference 0.8 to 0.9, as large as any in the data; urban origin reaches 0.89 too). The review reports the three scales within each sex of the respondent and finds the integration difference among men and among women alike, the optimism difference among women only. | F17: S2 Findings (No. 12 and 13); S4 Within sex | G17: Holds | H17: No change. | K17: 0
A18: 1.8 | B18: 1 | C18: Chapter 1, unit chart (eating less) | D18: Asked how they had coped with a fall in income, 73 percent of households outside the camp said they had eaten less, against 55 percent inside. | E18: Holds as a description of all households: 73% and 55%. Among comparable households (same pre-war traits, within the common support) the difference is 7 to 15 points and cannot be told from zero; the raw gap comes in good part from the traits that also decided where the household lives; the lower incidence of the shock in the towns works against the gap, and the response given the shock accounts for it (for the consumption cuts index, over all households, the incidence part is -0.11 and the part given the shock +0.47). | F18: S3 Figures; S4 Verdict and Shocks verdict (ate less); S4 Decomposition | G18: Holds with new wording | H18: Asked how they had coped with a fall in income, 73 percent of households in the towns said they had eaten less, against 55 percent in the camp. Among households with the same pre-war traits the gap is far smaller (7 to 15 points) and cannot be told from zero. | K18: 4
A19: 1.9 | B19: 1 | C19: Chapter 1, closing | D19: Households with more income cut food more often. The rest of the page explains why, and what it would have taken to change it. | E19: The premise weakens among comparable households (see 1.8). What the review can say: the shock (a fall in income) was less frequent in the towns (78% against 92%; 21 points fewer among comparable households, robust); among comparable households that suffered it, towns households cut consumption more (ate less 21 points more, cut other spending 25 points more) and drew less on savings and loans (17 and 20 points fewer), with no difference in the severe responses. Those conditional figures are descriptive. "What it would have taken to change it" is a causal counterfactual the design cannot support. | F19: S4 Decomposition (block B); S4 Shocks verdict; S4 How it was done (row 3) | G19: Revise | H19: Households in the towns have more income and more often report having eaten less. The rest of the page shows what goes with that: fewer of them suffered a fall in income, but among comparable households that did, more cut consumption and fewer drew on savings or loans. | J19: causal counterfactual | K19: 4
A20: Chapter 2. Before and after
A21: 2.1 | B21: 2 | C21: Chapter 2, opening | D21: Because every question was asked for Syria as well as for Jordan, the survey can be read as a two-period panel of the same household. | E21: Not supported. The survey is a single cross-section with recalled pre-war traits; each household is seen once, and matching on those traits or holding the year of arrival equal does not change that (step 3, part 8). Not every question was asked for Syria (see 1.2), the pre-war answers are recalled, and two of them carry gaps: income in Syria has no amount for 19 towns households (zero in the thesis variable) and spending in Syria none for 30. | F21: S3 Theory of change, part 8 (column H); S1 Findings (No. 15); S1 Variables | G21: Not supported | H21: The survey is a single cross-section taken in 2016. Its module on Syria before the war, answered from memory, gives the pre-war traits on which households are compared and a before-and-after picture of a few items (income, goods, savings, debts, work) that is read as recall, not as a second wave. | J21: "panel" | K21: 8
A22: 2.2 | B22: 2 | C22: Chapter 2, income before and after | D22: At one pre-crisis rate for everyone, camp households went from $465 a month to $220 and households outside from $495 to $384. | E22: The Jordan figures come close to the mean reported incomes (JD 162 in the camp and JD 277 in the towns, which at the page's rate of 1.405 give about $227 and $390). The Syria figures were not reproduced: the review keeps incomes in Syria in pounds (medians of 20 and 24 thousand a month; means of 26 and 32 thousand) because the conversion and the handling of blanks drive the dollar figures (19 towns households with no amount appear as zero in the thesis variable; the dollar variables of the thesis are empty where the year of arrival is missing or is 2016). The direction holds: camp households report the larger loss. | F22: Step 2 profile (means and medians of household income); S2 Before the war; S1 Findings (No. 15 and 16); S2 Findings (No. 16) | G22: Not checked | H22: Keep only after recomputing with blanks as missing and the pre-crisis rate stated, and report medians beside the means. Otherwise: in Syria the two groups reported similar incomes (medians of 20 and 24 thousand pounds a month); in Jordan the median is JD 140 a month in the camp and JD 270 in the towns. | K22: 1
A23: 2.3 | B23: 2 | C23: Chapter 2, income before and after | D23: Four in five camp households lost income; fewer than half outside did. | E23: Contradicted by the direct question: 92% of camp households and 78% of towns households report that their income fell since arrival, and the difference among comparable households is 21 to 25 points (robust). The page itself later counts 103 towns households that gave a cause for the fall. The computed version (converted amounts) depends on the conversion and on the blanks. | F23: S3 Figures; S4 Shocks verdict (income fell); S3 Theory of change, part 4 | G23: Revise | H23: Asked directly, 92 percent of camp households and 78 percent of households in the towns said their income had fallen since arrival; among comparable households the difference is about 21 points and holds under every test. | K23: 4
A24: 2.4 | B24: 2 | C24: Chapter 2, income before and after | D24: The thesis converted each family's income at the rate of the year it left Syria; read that way camp households lose little and households outside gain; since nominal pound incomes are the same across departure cohorts, this rate mostly records when a family left; it stays in the appendix. | E24: A methodological note the review did not test. One limit bears on it: the year of arrival is missing for 23 camp households and the month for 317 of 391, so an exit-year rate is undefined or coarse for many households. | F24: S1 Findings (No. 13 and 16) | G24: Not checked | H24: Keep as a note, adding that the year of arrival is missing for 23 camp households and the month for most households, so a rate by year of exit is undefined for some and coarse for the rest. | K24: 1
A25: 2.5 | B25: 2 | C25: Chapter 2, income before and after | D25: At purchasing power parity, households outside the camp are back at their pre-war standard of living and camp households are at about 60 percent of theirs; the factors are provisional, but the ranking does not depend on them. | E25: Not tested in the review, and subject to the same blanks and conversion caveats as 2.2. | F25: S1 Findings (No. 15 and 16) | G25: Not checked | H25: Keep only with the recomputation of 2.2; the ranking (a larger loss in the camp) is consistent with the pound and dinar figures. | K25: 1
A26: 2.6 | B26: 2 | C26: Chapter 2, income before and after | D26: Incomes in Syria were nearly identical (a standardised difference of 0.06), so the difference in within-household changes is about the same as the raw 2016 gap: $134 a month at the fixed rate, with a standard error of $61; the income advantage of households outside the camp was not inherited from Syria. | E26: The first part holds: recalled income in Syria hardly separates the groups (medians of 20 and 24 thousand pounds; the same median per person, 5 thousand). The $134 and its standard error were not reproduced (see 2.2). The design did not estimate the income level; it finds work income 24 points more frequent and spending per person about 1.9 times as high among comparable towns households (both robust). | F26: S2 Before the war; S2 Findings (No. 16); S4 Verdict (income from work; spending per person) | G26: Revise | H26: Recalled incomes in Syria hardly separate the two groups (medians of 20 and 24 thousand pounds a month), so the gap in Jordan was not inherited from Syria. Among comparable households, towns households more often have work income (24 points) and spend about 1.9 times as much per person. | K26: 1
A27: 2.7 | B27: 2 | C27: Chapter 2, goods chart (headline) | D27: Camp households lost the kitchen; households outside rebuilt it. | E27: The two goods hold as basic living conditions reached in Jordan: a refrigerator in 44% of camp households and nearly all in the towns; a stove in 23% and 74%. "Lost the kitchen" goes beyond the appliance count: cash for gas went to all camp families (REACH 2017), 82% of camp households had a separate kitchen in 2017 and 2018 (Fafo), and camp households cooked at home with gas while 23% report a stove, so the question appears to have counted the appliance. Use decided on 9 October 2026: report the two goods separately, as conditions reached in Jordan, and do not say camp households could not cook. | F27: S3 Checks, section 7; S3 Theory of change, part 5 | G27: Holds with new wording | H27: Fewer camp households have a refrigerator and a stove today; in the towns nearly all have a refrigerator and three in four a stove. | J27: headline says more than the count | K27: 5
A28: 2.8 | B28: 2 | C28: Chapter 2, goods chart | D28: Almost every household owned a refrigerator and a stove in Syria. In Zaatari fewer than one in four has a stove and fewer than half a refrigerator, because the caravan came without a kitchen; outside the camp, ownership of both is back near Syrian levels. | E28: The Syria figures hold (more than nine in ten households had each good) and the camp figures hold (23% and 44%). "Back near Syrian levels" holds for the refrigerator (nearly all) and not for the stove (74% against more than nine in ten in Syria). "Because the caravan came without a kitchen" is an explanation the survey does not test (see 2.7); the electricity supply (nine hours a day after 14 July 2016) bears on what a refrigerator was worth in the camp. | F28: S3 Checks, section 7; S3 Figures; S3 Literature (REACH 2016, AP 2016) | G28: Revise | H28: More than nine in ten households had a refrigerator and a stove in Syria. In Zaatari, 23 percent have a stove today and 44 percent a refrigerator; in the towns nearly all have a refrigerator and 74 percent a stove. Among comparable households the differences are 44 to 47 points for the stove and 30 to 40 for the refrigerator, and they hold under every test. | K28: 5
A29: 2.9 | B29: 2 | C29: Chapter 2, goods chart | D29: Counting four durable goods, camp households went from 3.3 items to 1.6 and households outside from 3.4 to 2.7. | E29: Not reproduced. The use decided on 9 October 2026 keeps the goods out of any wealth index between the camp and the towns, because much of what a household can hold depends on the place (electricity, space, what is provided in kind), and reports the refrigerator and the stove separately. The television (90% in the camp, nearly all in the towns) and the car (fewer than ten households in each group today) add little. | F29: S3 Checks, section 7 (use decided, point 2); S2 Before the war; step 2 profile (television and car today) | G29: Not supported | H29: Drop the count of items; report the refrigerator and the stove as in 2.8. | K29: 5
A30: 2.10 | B30: 2 | C30: Chapter 2, savings | D30: Half of the households later found outside the camp had savings in Syria, against fewer than one in five of those who stayed; by 2016 both groups were at [a share built on fewer than ten households]. | E30: The Syria figures hold (50% and 18%). The 2016 share rests on fewer than ten households in each group, so it cannot be printed as a percentage; the review states it as "fewer than ten in each group". | F30: S2 Before the war; S3 Checks, section 3; S2 Findings (No. 16) | G30: Holds with new wording | H30: Half of the households later found in the towns had savings in Syria, against fewer than one in five of those in the camp; by 2016 fewer than ten households in each group reported any savings. | I30: a share built on counts below ten | K30: 4
A31: 2.11 | B31: 2 | C31: Chapter 2, debt | D31: Debt rose from about a quarter of households to 60 percent in the camp and 69 percent outside, and since formal loans are nearly absent in Jordan, that debt is owed to shops, relatives and landlords. | E31: The shares hold (24% and 26% in Syria; 60% and 69% today; among comparable households 12 to 22 points more in the towns, fragile). The survey records no amount and no lender, so "owed to shops, relatives and landlords" rests on other studies: about 80% of indebted households owe to relatives and friends in Jordan (Fafo 2017-2018); refugees borrow mainly from neighbours (CARE 2017). Loans in Jordan are reported by fewer than ten households in each group. | F31: S3 Figures; S3 Theory of change, part 4 (columns D and G); S4 Verdict (has debts); S2 Before the war; step 2 profile (loans in Jordan) | G31: Holds with new wording | H31: Debt rose from about a quarter of households in Syria to 60 percent in the camp and 69 percent in the towns. The survey did not ask to whom; other surveys in Jordan find the debt owed mostly to relatives, friends and neighbours (Fafo 2017-2018; CARE 2017). | J31: cite the sources for the lender | K31: 4
A32: 2.12 | B32: 2 | C32: Chapter 2, work | D32: Work collapsed and recovered unevenly: nearly every household had an earner in Syria; in 2016, 39 percent of camp households did, mostly in incentive positions with NGOs and short weeks, against 64 percent outside, where those who work put in longer weeks than they did in Syria. | E32: The two shares hold as "a member works": 39% and 64% (work income among the sources: 36% and 67%; among comparable households 24 points more in the towns, robust). "Mostly in incentive positions with NGOs" and the comparison of weekly hours were not checked: the occupation labels are the respondent's, hours are usable with care, and the small occupation cells would need a protection pass. | F32: S1 Findings (No. 10); S3 Checks, section 2; S4 Verdict (income from work) | G32: Holds with new wording | H32: Nearly every household had an earner in Syria. In 2016 a member works in 39 percent of camp households and 64 percent of households in the towns; among comparable households the difference in work income is about 24 points and holds under every test. (The sentences on incentive positions and on weekly hours stay only after a check of the occupation and hours answers under the protection rule.) | K32: 1
A33: Chapter 3. Who left the camp
A34: 3.1 | B34: 3 | C34: Chapter 3, opening | D34: Until 2015 the legal way out of Zaatari was a Jordanian sponsor, which took means and contacts; the pre-displacement module lets the reader see directly what separated the two groups before anyone crossed the border, and it looks exactly like that. | E34: The rule is supported by the sources: the sponsor route was suspended in January 2015 (NRC and IHRC 2016); Zaatari residents could leave with a Jordanian relative as sponsor (Tobin et al. 2021). Households that left with a sponsor are over-represented in the sample (42 of 84 that passed through a camp, against 27% of exits in the UNHCR estimate). The module shows the means (savings, business, car, pension) and not the contacts: the survey did not ask whether the household had relatives or acquaintances in Jordan. | F34: S3 Literature; S2 Findings (No. 14); S3 Theory of change, part 0 (column H) | G34: Holds with new wording | H34: Until 2015 the legal way out of Zaatari was a Jordanian sponsor, which took means and contacts (NRC and IHRC 2016; Tobin et al. 2021). The module on Syria shows the means directly; the survey did not ask about contacts in Jordan. | K34: 0
A35: 3.2 | B35: 3 | C35: Chapter 3, balance chart | D35: Income in Syria, home ownership, household size, the respondent's age and the year of arrival are balanced. What differs is liquidity and origin: households now outside the camp had savings and a car far more often, came from towns rather than villages, had finished secondary school more often, and came less often from Daraa. | E35: Holds, with two traits missing from the list: an own business in Syria (37% and 65%) and a pension in Syria (fewer than ten camp households; 22% in the towns), which weigh in the selection model (odds ratios 3.5 and 6.9) beside urban origin (7.7) and savings (5.7). The balanced traits hold: income in Syria (medians 20 and 24 thousand pounds), owned home (92% in the camp and nearly all in the towns), household size (5.0 and 5.1), age (means 38.6 and 39.8), arrival by 2012 (44% and 46%). Schooling is the respondent's, not the head's. The page reads 0.25 as the threshold of imbalance; the Balance sheet of the review uses 0.1. | F35: S2 Before the war; S2 Findings (No. 16); S4 Sample and overlap (logit coefficients); S4 Balance | G35: Holds with new wording | H35: Add own business (37 against 65 percent) and pension in Syria (fewer than ten camp households against 22 percent in the towns) to the traits that differ, and say that schooling is the respondent's. | K35: 0
A36: 3.3 | B36: 3 | C36: Chapter 3, balance chart | D36: Selection into leaving the camp ran through the ability to arrange an exit, not through earning capacity. That is the selection the analysis has to absorb, and the pre-displacement outcomes make the adjustment testable: whatever reweighting works should leave no difference on life in Syria. | E36: The direction holds: the pre-war traits predict the place of residence well (area under the curve 0.87 for the nine-trait logit), urban origin and savings in Syria lead, and flexible models find no interaction the logit misses (0.85 against 0.85). "Not through earning capacity" rests on recalled income only, which has no amount for 19 towns households. The placebo on life in Syria was not reproduced; the review's placebo is different: six pre-war traits left out of the design barely predict residence (0.56) and, within the support with the weights, hardly at all (0.54 to 0.57); the placebo itself is settled in row 4.11. | F36: S4 Sample and overlap; S4 Flexible estimation (selection model and placebo); S1 Findings (No. 15) | G36: Holds with new wording | H36: What separated the two groups before the war was liquidity and origin (savings, a business, a pension, urban origin), not recalled income. Those traits predict where a household lives well, and six pre-war traits left out of the design add almost nothing, which is the check the comparison rests on. | K36: 0
A37: 3.4 | B37: 3 | C37: Chapter 3, closing | D37: The largest difference of all is who answered the questionnaire. | E37: Holds (see 1.7): standardized difference 0.8 to 0.9. | F37: S2 Findings (No. 12); S4 Within sex | G37: Holds | H37: No change. | K37: 0
A38: Chapter 4. After adjustment
A39: 4.1 | B39: 4 | C39: Chapter 4, opening | D39: Outcomes are grouped into seven domains, each an index in standard deviations of the camp and signed so that higher is better; camp households are reweighted so that their pre-displacement means match those of out-of-camp households. | E39: Replaced by the declared design. The uses decided on 9 October 2026 keep self-rated integration apart from happiness and optimism, the refrigerator and the stove out of any wealth index, the security scale read by its distribution, and the responses one by one with four declared indices (consumption cuts, financial buffers, severe responses, WFP severity score). Design 1 compares outcome levels between towns households and camp households with the same nine pre-war traits, within the common support (116 camp and 95 towns households), with augmented inverse probability weighting (AIPW) as the main estimator and four others as checks. | F39: S4 Verdict (header); S4 How it was done; S3 Checks, sections 7 and 8; S4 Indices | G39: Revise | H39: Twelve outcomes and the shocks and responses are compared one by one between towns households and camp households with the same pre-war traits (urban origin, savings, business, car, pension, vacations and origin in Daraa, household size, arrival by 2012), within the region where the two groups overlap. The scales and the two basic living conditions are reported in their own units; four declared indices summarise the responses. | K39: 0
A40: 4.2 | B40: 4 | C40: Chapter 4, title and throughout | D40: What living outside the camp did; the effect of living outside the camp. | E40: No causal design is available: the data hold no instrument, no discontinuity, no measure before displacement of the outcomes and no cohort structure that would separate the place from the households who chose it. Every figure of the review is a difference between comparable households, towns minus camp. | F40: S4 How it was done (row 3); S4 Verdict (header) | G40: Not supported | H40: Replace "effect of living outside the camp" everywhere by "difference between comparable households, towns minus camp", and say once that none of the differences is an effect of living in one place or the other. | J40: causal wording throughout the chapter | K40: 0
A41: 4.3 | B41: 4 | C41: Chapter 4, raw differences | D41: The raw differences are large in both directions: households outside the camp have more income, more assets and more work, and report much lower wellbeing, weaker social ties and less security. | E41: Income, spending, work and the two goods hold. "Wellbeing": self-rated integration 8.0 against 4.8 holds; optimism 6.1 against 5.1 and happiness 5.0 against 4.5 are smaller. "Social ties": the survey has no network measure beyond the first contact in an emergency (family or relatives 22% in the camp and 51% in the towns). "Less security" is not what the direct question shows: good or very good personal security is reported by 71% in the camp and 86% in the towns, very good by 52% and 33%; theft by 22% in the camp and fewer than ten towns households. | F41: S3 Theory of change, parts 6 and 7; S3 Checks, sections 1 and 8; S3 Figures | G41: Revise | H41: Before any adjustment, households in the towns have more income, more work and more of the two basic living conditions; they rate their integration far lower (4.8 against 8.0 on the 1 to 10 scale) and are somewhat less optimistic; on security the picture is mixed: more of them rate it good or very good, fewer rate it very good, and fewer report a theft. | K41: 6
A42: 4.4 | B42: 4 | C42: Chapter 4, after reweighting | D42: After reweighting camp households to match on savings, car, urban origin, schooling, Daraa origin, household size, age, arrival year, business and income in Syria, the income and work advantages shrink by half and stop being distinguishable from zero. Part of the raw gap was who left the camp. | E42: Contradicted for work and spending. Among comparable households, towns households name work income 24 to 30 points more often (raw 32; robust under the tier rule, fragile under the eight-trait specification) and spend 1.9 to 2 times as much per person (0.63 to 0.71 log points, robust). The income level itself was not estimated (recalled and converted amounts are used with care). Part of the raw gap does come from the pre-war traits. | F42: S4 Verdict (income from work; spending per person); S4 Estimates; S4 Flexible estimation | G42: Revise | H42: Among households with the same pre-war traits, the work and spending advantages of the towns shrink but remain: work income is 24 points more frequent (32 before adjustment) and spending per person about 1.9 times as high, and both hold under every test, including flexible machine-learning estimators. | K42: 1
A43: 4.5 | B43: 4 | C43: Chapter 4, three effects | D43: Assets (+0.9 SD; a hidden factor would have to multiply the odds of leaving the camp more than sixfold to explain it). | E43: Holds as two basic living conditions, not as an asset index (see 2.9): refrigerator 30 to 40 points more frequent among comparable towns households and stove 44 to 47 points, both robust; an unobserved trait would need to explain 26% and 28% of the residual variance in both the place and the outcome to remove significance, and a trait as strong as urban origin or savings in Syria barely moves them. | F43: S4 Verdict (refrigerator; stove); S4 Sensitivity | G43: Revise | H43: Among comparable households, 30 to 40 points more in the towns have a refrigerator and 44 to 47 points more a stove; no observed pre-war trait comes near the strength an unobserved one would need to remove the differences. | K43: 5
A44: 4.6 | B44: 4 | C44: Chapter 4, three effects | D44: Wellbeing and social ties (about -1.5 SD). | E44: Splits. Self-rated integration: camp households rate it about 3.2 points higher on the 1 to 10 scale among comparable households, the most robust difference of the twelve, among men and among women alike; read as a sense of belonging or comfort where the household lives, not as integration into Jordan. Optimism: 1 to 1.7 points higher in the camp, fragile, and found among women respondents (2.0 points) but not among men (0.6 to 0.9). Happiness: 0.5 to 0.9 points, cannot be told from zero. Folding the three into one index is the use the author set aside. | F44: S4 Verdict (integration; optimism; happiness); S4 Within sex; S3 Checks, section 8 | G44: Revise | H44: Comparable households in the camp rate their integration about 3 points higher on the 1 to 10 scale, among men and women alike; the answer is read as a sense of belonging where the household lives. They are also more optimistic, a difference carried by women respondents and fragile to the tests; in happiness the groups cannot be told apart. | K44: 7
A45: 4.7 | B45: 4 | C45: Chapter 4, three effects | D45: Security (-0.9 SD, robust in sign but fragile to hidden bias). | E45: Not supported as a difference against the towns. Among comparable households, good or very good personal security is 8 points more frequent in the towns and cannot be told from zero (raw 14 points). The mean of the five-level scale is the same in both groups (4.1) and the distribution differs at both ends. Theft cannot be estimated (fewer than ten towns households). "No one to turn to" is contaminated: 23 towns households left the first contact blank and nearly all of them appear as "has no one" in the thesis variable. | F45: S4 Verdict (personal security); S3 Checks, section 1; S1 Findings (No. 19); S3 Theory of change, part 6 | G45: Not supported | H45: On security the survey shows no difference among comparable households in the share rating it good or very good; camp households give more answers at both ends of the scale; theft is reported by 22 percent of camp households and by fewer than ten in the towns; the first contact in an emergency differs (the police for 69 percent in the camp and 23 percent in the towns, family or relatives for 22 and 51 percent). | K45: 6
A46: 4.8 | B46: 4 | C46: Chapter 4, three effects | D46: Comparable households outside the camp are also more often in debt. | E46: Holds as a fragile difference: 12 points in ordinary least squares (OLS) and 22 with AIPW; it clears the AIPW test but not the OLS one nor the correction for twelve outcomes. | F46: S4 Verdict (has debts) | G46: Holds with new wording | H46: Comparable households in the towns also report debts more often (12 to 22 points), a difference that clears some tests and not others. | K46: 3
A47: 4.9 | B47: 4 | C47: Chapter 4, minimum detectable effect | D47: The shaded band is the minimum effect the sample can detect, about 0.30 SD; with 134 treated households and an effective control sample of about 40 after reweighting, estimates inside the band say something about direction and little about size. | E47: The limit holds and the numbers change: within the support, 95 towns households and 116 camp households worth 53 equally weighted ones after reweighting (28 on the whole sample); the minimum detectable difference is about 20 to 25 points for a yes or no outcome, 0.40 log points for spending per person and 1.3 to 1.4 points on the 1 to 10 scales. | F47: S4 Sample and overlap; S4 Power | G47: Revise | H47: Within the region where the two groups overlap, 95 households in the towns are compared with 116 in the camp, worth about 53 after reweighting; the sample cannot separate from zero a difference smaller than about 20 to 25 points in a yes or no outcome or 1.3 to 1.4 points on a 1 to 10 scale. | K47: 0
A48: 4.10 | B48: 4 | C48: Chapter 4, estimators | D48: The other estimators agree on the sign of every index except coping, where every estimate is close to zero. | E48: Revised. In the responses the estimates are not all close to zero: used savings 22 to 26 points fewer in the towns (robust), loans 19 to 21 fewer (fragile), cut other spending 14 to 17 more (fragile), ate less 7 to 15 more (null), number of responses 0.3 to 0.8 fewer (fragile). Among the four indices, the financial-buffers index is fragile and the others null within the support. Sign agreement across the five adjusted estimators holds for every robust outcome. | F48: S4 Shocks verdict; S4 Indices; S4 Verdict (column L) | G48: Revise | H48: The five adjusted estimators agree on the sign of every robust difference. In the responses to a fall in income, comparable towns households drew on savings less often (22 to 26 points, robust) and on loans less often (19 to 21 points, fragile); eating less (7 to 15 points more) cannot be told from zero and cutting other spending (14 to 17 points more) is fragile. | K48: 4
A49: 4.11 | B49: 4 | C49: Chapter 4, placebo | D49: Placebo: the same estimators on life in Syria; pre-displacement outcomes not used for reweighting; after adjustment there should be nothing here. | E49: Not reproduced. The pre-war goods sit above 90% in both groups, so there is almost nothing to test on them, and income in Syria is recalled with gaps. The review's check is different: six pre-war traits left out of the design (outings, debts, informal work, owned home, loans and income in Syria) predict residence poorly alone (area under the curve 0.56) and, within the support with the weights, hardly at all (0.54 to 0.57). | F49: S4 Flexible estimation (placebo); S3 Checks, section 7 | G49: Revise | H49: Replace the placebo chart with the left-out traits check: six pre-war traits not used in the design barely predict where a household lives, before and after reweighting. | K49: 0
A50: 4.12 | B50: 4 | C50: Chapter 4, hidden bias | D50: Robustness values: the share of residual variance an unobserved confounder would need to explain to erase the estimate; savings, the respondent's gender and urban origin, the strongest observed selection variables, each explain about one percent or less. | E50: The method holds and the numbers change. Robustness values to bring the difference to zero: 0.23 (work income), 0.35 (refrigerator), 0.37 (stove), 0.33 (spending), 0.38 (integration). The benchmarks: urban origin explains 12 to 16% of the residual variance of the place and 3% or less of the outcome; savings in Syria 3 to 7% and 6% or less (the shocks family included); so "one percent or less" holds for the outcome side only. The respondent's sex was not benchmarked (it enters the outcome model, not the design). | F50: S4 Sensitivity | G50: Revise | H50: An unobserved pre-war trait would need to explain about a quarter to a third of the residual variance of both the place of residence and the outcome to bring the robust differences to zero; urban origin and savings in Syria, the strongest observed traits, explain up to 16 percent of the place and 6 percent or less of any outcome. | K50: 0
A51: Chapter 5. Why
A52: 5.1 | B52: 5 | C52: Chapter 5, opening | D52: The thesis's most counterintuitive result was that the households with more income cut food more often. Three things explain it, and each of them could have been changed by a programme. | E52: The thesis estimate (+28 points with one nearest neighbour on the whole sample) is reproduced; under design 1 the difference among comparable households is 7 to 15 points and null. What the review finds instead: fewer towns households suffered a fall in income, and among comparable households that did, more cut consumption (21 and 25 points) and fewer drew on savings and loans. "Explain" and "could have been changed" are causal claims the design does not support; what the page can show is what goes with the cut. | F52: S4 Thesis table; S4 Verdict (ate less); S4 Decomposition (block B) | G52: Revise | H52: The thesis found that households with more income cut food more often. Compared like with like, that gap shrinks and cannot be told from zero; among comparable households whose income fell, however, those in the towns cut consumption more and drew less on savings and loans. Three things go with that pattern. | J52: causal ("explain", "could have been changed") | K52: 4
A53: 5.2 | B53: 5 | C53: Chapter 5, budget shares | D53: Outside the camp, rent takes a third of spending; inside, food takes three quarters because shelter, water and school come with the caravan. | E53: Recomputed in step 5b with blanks as missing (no spending item has a written zero, so a blank is treated as no answer), over the households with a reported total above zero (239 in the camp, 121 in the towns), as the sum of each item over the sum of the totals. Camp: food is 77% of the group total (reported by 221 of the 239 households; among them the median share of food in the household total is 89%), other items as written 3% (22 households) and transport 1.5% (34); rent, electricity, water and education are each reported by fewer than ten camp households and are folded, with the part of the total not covered by the items read (which holds any health spending), into a remainder of 19%. Towns: rent is 35% of the group total (95 of 121 households; median share 47% among them), food 33% (98 households; median share 37%), electricity 5%, water 4%, transport 3%, other items 3%; education is reported by fewer than ten households and is folded into the remainder (17%). The page's "a third" and "three quarters" stand; its shares were computed with blanks as zero. | F53: Step 5b, section A (technical note, Table 4.4 and Figure 4.1); S1 Findings (No. 12) for the blank rule | G53: Holds with new wording | H53: Outside the camp, rent takes 35 percent of reported spending and food 33 percent; inside, food takes 77 percent, because shelter, water and schooling come with the caravan. (Shares with blanks as missing, as the sum of the item over the sum of the totals; among the households that report the item, the median share is 47 percent for rent in the towns and 89 percent for food in the camp.) | K53: 2
A54: 5.3 | B54: 5 | C54: Chapter 5, where the money goes | D54: Households outside the camp earn almost twice as much as camp households and spend almost twice as much. | E54: Holds: median income JD 140 a month in the camp and JD 270 in the towns; median spending JD 125 and JD 250; per person, JD 20 and 53 (income) and JD 27 and 56 (spending). Among comparable households, spending per person is about 1.9 times higher in the towns (robust). | F54: Step 2 profile (medians of household income and spending); S3 Figures (per person); S4 Verdict (spending per person) | G54: Holds | H54: No change; the medians can be given (JD 140 against 270 in income, JD 125 against 250 in spending). | K54: 1
A55: 5.4 | B55: 5 | C55: Chapter 5, where the money goes | D55: Once rent is paid, the two groups are living on the same money: income after rent per person is 39 dinars outside and 36 in the camp, and food spending per person is 27 against 29. | E55: Food spending per person holds as means (JD 26.7 in the towns and 28.8 in the camp); the medians are JD 20 in both groups. Income after rent was computed in step 5b, with blanks as missing, for the 104 towns households that rent with an income and a rent reported: JD 32 per person a month at the median (quartiles 18 and 46; mean 35). In the camp fewer than ten households pay rent, so income after rent is income: a median of JD 20 per person (quartiles 20 and 42; mean 38; step 2 profile, 248 households with an income reported). The page's 39 and 36 are means with blanks as zero. On means the two figures are close (35 and 38); at the median they are not (32 against 20), because most camp incomes sit at the value of the voucher. The reading "the same money" is a description, not a test. | F55: Step 2 profile (food spending per person and income per person: means, medians and quartiles); step 5b, section B (technical note, Table 4.5) | G55: Holds with new wording | H55: Food spending per person is about the same in the two groups (means of JD 29 in the camp and 27 in the towns; medians of JD 20 in both). Once rent is paid, towns households that rent have on average about the same income per person as camp households (means of JD 35 and 38), though not at the median (JD 32 against 20), since most camp incomes sit at the value of the voucher. | K55: 2
A56: 5.5 | B56: 5 | C56: Chapter 5, where the money goes | D56: Camp households put three quarters of their spending into food because water, shelter, schooling and most health care come with the caravan; households outside pay for electricity, water, transport and school. | E56: The share is recomputed in step 5b (row 5.2): food is 77% of the reported spending of camp households, with blanks as missing. The account of what each place provides matches the sources (eight free medical facilities and Ministry schools in the camp, UN Jordan 2022; health fees outside the camps since November 2014, Doocy et al. 2016). | F56: Step 5b, section A (technical note, Table 4.4); S3 Literature (UN Jordan 2022; Doocy et al. 2016); S3 Theory of change, part 2 | G56: Holds with new wording | H56: Three quarters of what camp households spend (77 percent of reported spending) goes to food, because water, shelter, schooling and most health care come with the caravan; households in the towns pay for rent, electricity, water, transport and, since November 2014, health care. | K56: 2
A57: 5.6 | B57: 5 | C57: Chapter 5, assistance | D57: Assistance is not the difference either: by mid-2016 nine in ten households in both groups received some, WFP vouchers for most of them, and per person it came to about 19 dinars in the camp and 23 outside; what differed was what assistance was relative to the budget: three quarters of income in the camp, half of it outside. | E57: Coverage holds: about nine in ten households in each group name some assistance (the voucher: 93% of camp households and 86% of towns households). The amounts do not: the voucher is JD 20 per person for 206 of 230 camp households and comes in two tiers in the towns (52 households above JD 12 per person, 61 at or below; median JD 10); all assistance per person has medians of JD 20 in the camp and 17 in the towns. The weight holds in direction: 64% of camp households and 33% of towns households report no work income among their sources, most of the former living on the voucher alone (the share living on assistance alone is no longer printed: with the work-income count and the answering base it fixed a count below ten). Towns households name the 2015 cut as the cause of their fall in income (89 of 103); camp households name prices. Two support packages, then: uniform and stable in the camp, tiered and cut in the towns, where the Jordanian state and organizations both reach households. | F57: S2 Findings (No. 4 and 9); S3 Figures (work income among the sources); S3 Theory of change, parts 1 and 4; step 2 profile (voucher per person); S4 Shocks described | G57: Revise | H57: Assistance reaches nine in ten households in both groups, but as two different packages. In the camp 93 percent of households name the voucher, nine in ten of them at exactly JD 20 per person, and six households in ten report no income from work. In the towns it comes in two tiers (median JD 10 per person) and was cut in August 2015; a third of households report no income from work, and UNHCR cash reaches three in ten. | K57: 1
A58: 5.7 | B58: 5 | C58: Chapter 5, rent burden | D58: The median household outside the camp pays 35 percent of its income in rent and a quarter pay more than 56 percent; food cuts rise with that burden, from 59 percent of households in the lowest third to [a share whose complement is below ten] in the highest. | E58: Computed in step 5b, declared beforehand, for the 104 towns households that rent with an income and a rent reported, blanks as missing. Rent takes 44% of reported income at the median (quartiles 31% and 63%; mean 65%, pulled up by the 11 households whose rent is at or above their reported income). Thirds of the rent share (cut points at 34% and 55% of income; 35, 34 and 35 households; median shares of 28%, 44% and 75%): ate less, 22 of 35 households in the lowest third (63%) and nearly all in the middle and the highest thirds; cut other spending, the same pattern; debts today, 21 of 35 in the lowest third (60%) and nearly all in the highest; a loan, fewer than ten households in the lowest and the middle thirds and 15 of 34 in the highest (44%); savings spent, 20 of 35, 19 of 33 and 22 of 33. Where a cell reads "nearly all" the margin of the difference between thirds is not computed. The page's 35 and 56 percent were computed with blanks as zero. The cut conditions on rent, observed after the place of residence, so it describes towns households. | F58: Step 5b, sections B and C (technical note, Tables 4.5 and 4.6, Figure 4.2); S1 Variables (rent, income) | G58: Revise | H58: Among towns households that rent, rent takes 44 percent of reported income at the median, and a quarter of them pay more than 63 percent. Food cuts rise with that burden: 63 percent of households in the lowest third of the rent share ate less, and nearly all in the middle and the highest thirds; nearly all households in the highest third carry debt. This describes towns households and does not compare the two groups. | I58: The page's share for the highest third (about forty households) fixes the households that did not eat less below ten; the recount prints "nearly all". | K58: 2
A59: 5.8 | B59: 5 | C59: Chapter 5, why income fell | D59: Camp households named prices; out-of-camp households named the cut of August 2015, when WFP, short of funds, cut the value of its vouchers for refugees outside the camps to about 14 dollars a person a month for the neediest tier (the page uses the word the author avoids) and 7 dollars for the rest, and kept camp residents at the full value. | E59: Holds: in the camp, prices (152 of 233 households that gave a cause), the cut in assistance (42) and lack of work (39); in the towns, the cut in assistance (89 of 103). The programme figures are confirmed at their source, read for this step: in August 2015 WFP kept full assistance in the camps (USD 28.2 per person a month) and, in the communities, paid USD 14.1 to the refugees it ranked in its highest-need category (half of the planned amount, through November) and USD 7.05 to the others, who were excluded from September; assistance to nearly 229,000 refugees in communities stopped that month (WFP, Situation Update: Syria Crisis Regional Response, July 2015, issued 20 August 2015; WFP Jordan Situation Report, August 2015). The sources read in steps 2 and 3 carry the later tiers of February 2016 (JD 20 and JD 10 per person; S2 Calculations and Comparison No. 47). | F59: S3 Theory of change, part 4; S3 Figures; S4 Shocks described; WFP 2015 (regional situation update, July 2015, and Jordan situation report, August 2015), read for this step | G59: Holds with new wording | H59: Camp households named rising prices (152 of 233 that gave a cause); households in the towns named the cut of August 2015 (89 of 103), when WFP, short of funds, reduced the voucher for refugees outside the camps to about 14 dollars a person a month for the households in its highest-need category and 7 dollars for the rest, who lost it altogether in September, and kept camp residents at the full value of about 28 dollars (WFP 2015). | J59: the word the author avoids; the source is now cited | K59: 4
A60: 5.9 | B60: 5 | C60: Chapter 5, why income fell | D60: 89 of the 103 out-of-camp households that gave a reason named a reduction of assistance; [a share whose complement is below ten] of them had eaten less. | E60: The 89 of 103 holds. The share of those 89 that ate less has a complement below ten households, so it reads "nearly all"; the same holds for cutting other spending. Among them, 72% spent savings, 69% asked for assistance, 39% sold belongings and in 37% a child went to work. | F60: S3 Theory of change, part 4 (column F); S4 Decomposition (block C) | G60: Holds with new wording | H60: 89 of the 103 households in the towns that gave a reason named a reduction of assistance, and nearly all of them had eaten less. | I60: a share whose complement is below ten | K60: 4
A61: 5.10 | B61: 5 | C61: Chapter 5, food cuts | D61: Put together, the raw gap of 18 points in food cuts between households outside and inside the camp falls to 10 once rent and income after rent are held fixed, and to 4 once the households that attributed their loss of income to the assistance cut are marked; those households were 27 points more likely to have cut food. | E61: Not reproduced, and the model conditions on variables observed after the place of residence (rent, income after rent, the reported cause), which the review's reading rule treats as descriptive. The review's route: among comparable households the gap is 7 to 15 points and null; among comparable households whose income fell, towns households ate less 21 points more often (p = 0.003) and cut other spending 25 points more often, drew on savings 17 points less often and on loans 20 points less; among households naming the cut in assistance, 62% in the camp ate less and nearly all in the towns. | F61: S4 Decomposition (blocks B and C); S4 Verdict (ate less); S4 How it was done (row 13) | G61: Revise | H61: Compared like with like, the 18-point gap in eating less shrinks to 7 to 15 points and cannot be told from zero. Among comparable households whose income fell, however, those in the towns ate less 21 points more often and cut other spending 25 points more often, while drawing less on savings and loans; these are descriptions of the households that suffered the shock, not estimates of what the place did. | K61: 4
A62: 5.11 | B62: 5 | C62: Chapter 5, food cuts | D62: The attribution is their own account, so that number dates the shock rather than measuring its effect. | E62: Holds, and the caution extends to every figure built on the reported cause: the cause is used only as coded categories. | F62: S4 How it was done (rows 13 and 20) | G62: Holds | H62: No change. | K62: 4
A63: 5.12 | B63: 5 | C63: Chapter 5, food cuts | D63: The result the thesis found puzzling was rent, and a policy shock that hit one group and not the other in the year before the survey. Both are things a programme could have changed. | E63: The association holds (rent outside, the 2015 cut named by 89 of 103 towns households); "was rent" and "could have changed" state causes the design does not identify. Other studies supply the causal evidence on transfers: consumption rises and borrowing falls while a transfer lasts and the gains disappear after it ends (Altındağ and O'Connell 2023); cuts and delays in assistance hit food consumption (Bruni and Sterck 2025); a rent subsidy lowered housing spending and reliance on loans while it lasted (Tamim et al. 2025). | F63: S3 Literature; S3 Theory of change, part 4 (column G) | G63: Revise | H63: What goes with the puzzle is rent, which towns households pay and camp households do not, and the 2015 cut, which fell on one group and not the other in the year before the survey. Experiments elsewhere show that while a transfer lasts consumption rises and borrowing falls, and that the gains disappear after it ends (Altındağ and O'Connell 2023); a rent subsidy lowered housing spending and reliance on loans while it lasted (Tamim et al. 2025). | J63: causal | K63: 4
A64: 5.13 | B64: 5 | C64: Chapter 5, what a transfer would have done | D64: Predicted change in the share of out-of-camp households cutting food, from the rent-burden model; rent support is the instrument that moves the outcome, and the most expensive per household; portable vouchers do little in 2016 because per-person assistance outside the camp had recovered to the camp level by then. | E64: Not supported as a prediction: it extrapolates a descriptive regression that conditions on post-residence variables into a counterfactual, which the review's rules exclude ("nothing in the files is an estimate of an effect"). The premise that assistance per person outside had recovered to the camp level does not hold in the data (voucher medians of JD 10 and JD 20; all assistance JD 17 and JD 20 per person). | F64: S4 How it was done (row 3); S3 How it was done (rule 5); S3 Figures (assistance per person); step 2 profile (voucher per person) | G64: Not supported | H64: Drop the panel. If the page wants to say what a transfer does, cite the experiments (Altındağ and O'Connell 2023; Tamim et al. 2025) rather than a prediction from these data. | J64: counterfactual | K64: 4
A65: 5.14 | B65: 5 | C65: Chapter 5, registration | D65: Of the twelve out-of-camp households still awaiting registration, none received WFP vouchers and none received UNHCR cash, against 93 and 32 percent of registered refugees; [a share built on fewer than ten households] received assistance of some other kind; their incomes were no lower, but [a share whose complement is below ten] cut food against seven in ten; registration gated assistance, exactly as the documentation literature says, and the survey shows it with twelve households. | E65: Two shares of the twelve rest on counts below ten and one has a complement below ten; the income comparison of twelve households cannot be reported either. The twelve are all the variation the survey has (fewer than ten camp households and no unregistered household), so the question cannot carry a comparison. The gate itself is documented in the sources (NRC and IHRC 2016). | F65: S1 Findings (No. 14); S2 Findings (No. 17); S3 Literature (NRC and IHRC 2016) | G65: Not supported | H65: Drop the panel and the comparison. At most one sentence: twelve households in the towns reported being still registered as asylum seekers, and none of them reported the voucher or UNHCR cash; the rules that tied assistance to registration are described in NRC and IHRC (2016). | I65: two shares built on counts below ten and one with a complement below ten; a cut of twelve households | K65: 1
A66: 5.15 | B66: 5 | C66: Chapter 5, registration | D66: Among the routes out of the camp, households that left informally report far lower personal integration (3.7 against 5.7 on a ten-point scale for sponsored households) and are the group most often without anyone to call in an emergency. | E66: The first half holds under the name decided, with the level the step 3 workbook uses since 21 October 2026: self-rated integration (1 to 10) of 4.0 among households that left informally, by another route or without saying how (every household that passed through a camp and does not report a sponsor), and 5.7 among those that left with a sponsor, a difference beyond the margin. The second half is not supported: 23 towns households left the first contact blank and nearly all of them appear as "has no one to turn to" in the thesis variable; a blank is a missing answer. | F66: S3 Checks, section 8; S3 Theory of change, part 7 (column F); S1 Findings (No. 19) | G66: Revise | H66: Among households that passed through a camp, those that left without a sponsor (informally or by another route) rate their integration lower than those that left with one (4.0 against 5.7 on the 1 to 10 scale). (The sentence on having no one to call goes: the blank answers were counted as "no one".) | J66: name of the scale | K66: 7
A67: 5.16 | B67: 5 | C67: Chapter 5, an average day | D67: Coded answers to an open question, by group and gender of the respondent: "nothing" was said only in the camp; outside, the idle answer is "sitting in the house" and the largest category is housework and care, the answer of 54 percent of women against 32 percent of men. | E67: Recounted in step 5b from the coded categories of the household file, with blanks as missing: 256 camp respondents and 133 towns respondents answered. The categories with ten households or more in the whole sample are kept (nothing; working; sitting in the house; taking care of the house, with the answers cut short as "taking"; watching sports) and the rest form "other answers"; no answer is quoted. In the camp, "nothing" is the answer of 162 of 256 respondents (63%), of men (125 of 201) and women (37 of 55) alike; working follows (35 of 256) and watching sports (26, all of them men). In the towns no respondent answered "nothing" or "watching sports": taking care of the house is the answer of 60 of 133 (45%), of 44 of the 83 women (53%) and 16 of the 50 men (32%); sitting in the house, 41 of 133 (31%); working, 20 of 133 (15%). Cells below ten read "fewer than 10", and a second cell is withheld where the first could be worked out from the totals (five cells of the table by sex). The page's 54 and 32 percent were counted with blanks as zero. | F67: Step 5b, section D (technical note, Table 7.10 and Figure 7.3); S1 Summary (block 11); S1 Variables (average day) | G67: Holds with new wording | H67: Coded answers to an open question, by group and sex of the respondent: "nothing" was the answer of 63 percent of respondents in the camp and of no one in the towns; outside the camp the day is taking care of the house, the answer of 53 percent of the women and 32 percent of the men who answered, or sitting in the house (31 percent). The table describes the person who answered: mostly men in the camp, mostly women in the towns. | J67: "The idle answer" reads the answer for the respondent; the category is printed as coded. | K67: 7
A68: 5.17 | B68: 5 | C68: Chapter 5, an average day | D68: Among respondents without a job, 80 percent in the camp describe their day as nothing or sitting at home, against 37 percent outside; with employment and household characteristics held fixed, the camp adds about 41 points to the probability of an empty day. | E68: Not checked. Conditioning on the respondent's own employment is right for a question about the respondent's day (employment describes the respondent, not the household). "The camp adds" is causal wording; the figure would be a difference between respondents with the same traits. | F68: S3 Checks, section 2 (whom the work questions describe) | G68: Not checked | H68: Keep only after recomputation under the blank rule, worded as a difference: among respondents without a job and with the same household traits, those in the camp describe an empty day about 41 points more often. | J68: causal ("adds"); the ethnographies of Zaatari and Azraq are not named | K68: 7
A69: 5.18 | B69: 5 | C69: Chapter 5, empty days by district | D69: Share of respondents describing their day as nothing or sitting at home, by Zaatari district, districts with at least ten interviews. | E69: Not checked. The cut by district is allowed for this question (health is the item never crossed with district). The threshold of ten interviews per district is necessary but not sufficient: a share in a district of ten to nineteen interviews can reveal a count below ten (for example nine of ten), so each district needs both cells at or above ten or the share withheld. | F69: S4 How it was done (row 20); S3 How it was done (protection rule) | G69: Not checked | H69: Keep only for districts where both the respondents with an empty day and the others number ten or more; otherwise merge districts. | I69: district shares can reveal counts below ten | K69: 7
A70: 5.19 | B70: 5 | C70: Chapter 5, empty days | D70: Within the camp, respondents with empty days report no less happiness or optimism than the others, and they report more personal security (4.3 against 3.7 on a five-point scale) and family integration; the camp's empty days come with safety and with a dense community. | E70: Not checked. The security scale is read by its distribution (good or very good), not by its mean, because the two formats were joined and the boundary between good and very good is the sensitive one; within the camp the format is one (numbers), so a mean is less exposed, but the agreed reading still applies. "Family integration" is self-rated integration (1 to 10), which is not a measure of networks, so "dense community" says more than the question. | F70: S3 Checks, sections 1 and 8 | G70: Not checked | H70: Keep only after recomputation as shares (good or very good security; self-rated integration at 7 to 10) under the blank rule; say "a stronger sense of belonging" rather than "a dense community". | J70: name of the scale; "community" beyond the question | K70: 7
A71: Data, methods and limits
A72: M.1 | B72: M | C72: Methods, survey | D72: Out-of-camp households were reached through the towns rather than through UNHCR files, so the sample includes families that registered-only surveys cannot see. | E72: The first part holds and gains precision: households in the towns were reached by referral within groups set beforehand (stratified snowball sampling), by day and at home, so no sampling frame covers them and the towns group over-represents Irbid and Ramtha, early arrivals and households that left with a sponsor. The second part is thin: twelve towns households reported being asylum seekers and none reported being unregistered. | F72: S3 How it was done (author's account, 8 October 2026); S2 Findings (No. 5, 6, 14 and 17) | G72: Revise | H72: Households in the towns were reached by referral from other households, by day and at home, not through agency lists; the sample covers the northern towns (two thirds in Irbid and Ramtha), over-represents households that left the camp with a sponsor, and includes twelve households still registered as asylum seekers. | K72: 0
A73: M.2 | B73: M | C73: Methods, design | D73: Two-period household panel by recall (Syria before displacement, Jordan 2016); pre-displacement values serve as balancing covariates and as placebo outcomes. | E73: Not supported as a panel (see 2.1). The pre-war traits do serve as balancing covariates; the placebo on pre-war outcomes was replaced by the left-out traits check (see 4.11). | F73: S3 Theory of change, part 8; S4 Flexible estimation | G73: Not supported | H73: A single cross-section of 2016 with a recalled module on Syria before the war; the pre-war traits serve to compare like with like, and six pre-war traits left out of the design serve as the check. | J73: "panel" | K73: 8
A74: M.3 | B74: M | C74: Methods, estimand | D74: Effect of living outside the camp for the households that did (ATT), under selection on pre-displacement observables. | E74: The reference population holds (towns households, with camp households reweighted to them); the word "effect" does not (see 4.2). The sample of design 1 is the households with every design and respondent trait observed (48 camp households and fewer than ten in the towns are left out), within the common support (116 camp and 95 towns households). | F74: S4 Verdict (header); S4 Sample and overlap | G74: Holds with new wording | H74: Differences between towns households and camp households with the same pre-war traits, with the towns as the reference population, within the region of common support; not an effect of living in either place. | J74: "effect" | K74: 0
A75: M.4 | B75: M | C75: Methods, estimators | D75: Entropy balancing on first moments (main); augmented inverse probability weighting; 1:1 nearest-neighbour matching with a 0.2 caliper; OLS; robust and stratified-bootstrap standard errors; Rosenbaum bounds on matched pairs; Cinelli and Hazlett robustness values; Benjamini and Hochberg q-values across indices. | E75: Replaced by design 1 as declared before running: AIPW as the main estimator; inverse probability weights, entropy balancing, bias-adjusted nearest neighbour and OLS as checks; common support 0.1 to 0.9 with the score re-estimated within it; a bootstrap that resamples households within the strata of the sampling design (400 draws) and a linearized design-based error for OLS; Romano and Wolf stepdown within each family; Oster and Cinelli and Hazlett sensitivity; minimum detectable differences; an eight-trait specification, the scales within each sex, and a double machine learning check (forests, boosting, lasso) in which no estimate leaves the parametric interval. A blind replication by a separate instance of the AI assistant compared 1,261 quantities: no point estimate, count or verdict changed; the differences in some bootstrap errors are explained on the sheet, and two implementation choices were corrected after the replication. | F75: S4 How it was done; S4 Blind replication; S4 Flexible estimation | G75: Revise | H75: State design 1 as the method: AIPW with four checks, common support, strata bootstrap, Romano and Wolf, Oster, Cinelli and Hazlett, minimum detectable differences, the eight-trait check, the within-sex scales, the machine-learning check and the blind replication. | K75: 0
A76: M.5 | B76: M | C76: Methods, conversions | D76: Syrian pounds at a fixed pre-crisis rate (main), at purchasing power parity (welfare version, provisional factors), and at the rate of the year each family left (thesis); dinars at 1.405 USD. | E76: Not tested. The review reports incomes in pounds and dinars and uses no dollar figure; the thesis dollar variables are empty where the year of arrival is missing or is 2016. | F76: S1 Findings (No. 16) | G76: Not checked | H76: Keep as a note if the dollar figures stay (see 2.2); say that incomes in Syria are reported in pounds and in Jordan in dinars in the tables. | K76: 1
A77: M.6 | B77: M | C77: Methods, sample decisions | D77: All 391 households in the file (the 2017 thesis used [a number that leaves a count below ten]; the reason for the exclusions was not recorded); Syrian spending outside the camp is treated as item nonresponse: responders were richer and more often men, so the before-and-after of spending is reported for the camp only. | E77: Holds, with one count to mask: the do-file (the Stata script of the thesis) drops fewer than ten households by file number without recording the reason, and the page gives the thesis total, which fixes that count. The treatment of Syrian spending as nonresponse matches the review (30 towns households with no answer appear as zero in the thesis variable). The review adds a rule the page does not state: a blank is a missing value, never a zero, in every variable; the analysis sample of design 1 keeps the households with every design trait observed, and the 48 camp households left out (no year of arrival, no rural or urban origin or no place of origin) differ from the rest (more savings, more origin in Daraa); fewer than ten towns households are left out. | F77: S1 Findings (No. 15 and 21); S4 How it was done (row 5); S1 How it was done | G77: Holds with new wording | H77: All 391 households in the file (the thesis dropped fewer than ten, without recording the reason). A blank answer is treated as missing, never as zero. Spending in Syria is missing for 30 households in the towns and is reported for the camp only. The adjusted comparisons use the households with every pre-war trait observed; 48 camp households and fewer than ten in the towns are left out. | I77: the thesis total fixes a count below ten | K77: 0
A78: M.7 | B78: M | C78: Methods, limits | D78: Overlap is thin (effective control sample of about 40 households); the minimum detectable effect is about 0.30 SD; subjective outcomes are answered by different people in the two groups; the exit-timing status proxy cannot be tested in this sample; pre-displacement values are recalled, and recall may differ between the groups; the map places households at their governorate of origin and town of interview. | E78: Holds and grows. Update the numbers (116 camp households worth 53 within the support; minimum detectable differences by outcome). Add the sampling limits: referral sampling in the towns, fewer than ten households in Amman and in Mafraq, early arrivals and sponsored exits over-represented, the camp with fewer households reporting work than Fafo found in 2017 and 2018; the 48 camp households without a complete pre-war profile; a single health question read as a minimum; the security scale recorded in two formats; the open question on integration into what. | F78: S4 Sample and overlap; S4 Power; S2 Findings (No. 5, 6, 10, 11, 14); S3 Checks, sections 1 and 8 | G78: Revise | H78: Keep the paragraph and add: households in the towns were reached by referral, in the northern towns only; early arrivals and sponsored exits weigh more than in the population; 48 camp households lack a complete pre-war profile and are left out of the adjusted comparisons; health enters through one yes or no question; the security scale was recorded as numbers in the camp and as words in the towns. | K78: 0
A79: M.8 | B79: M | C79: Methods, ethics and data protection | D79: The page publishes aggregates only; no statistic is reported for a subgroup of fewer than ten households; flows on the map are drawn only for pairs with at least five households; open-ended answers appear only as coded categories. | E79: The rules hold and the page breaks its own rule in seven places: the route counts (1.4), the registration counts and the ring (1.6), the savings share (2.10), the share of the highest third of the rent burden that ate less (5.7, found in step 5b), the share of the 89 that ate less (5.9), the registration panel (5.14) and the thesis total (M.6). Each has a wording above. | F79: This table, entries 1.4, 1.6, 2.10, 5.7, 5.9, 5.14 and M.6 | G79: Holds with new wording | H79: Keep the paragraph; apply the seven corrections listed in this table before the page is republished, in English and in Spanish. | I79: the page prints or lets a reader work out counts below ten in seven places | K79: 0
A80: M.9 | B80: M | C80: Methods, reproducibility | D80: Every figure and table on the page is generated from three results files, one per module, produced by three scripts from the survey file; the scripts are not published at this stage; the household file is not in the repository. | E80: Holds as a statement about the page. The review's scripts (d0_frame, e_lib, e3_design1, e4_inference, e7_decomposition, e9_ml and the step 1 to 3 scripts) run on the author's computer and output aggregates only; the household file never leaves it. Neither set is published, by the author's standing decision: the household file and the scripts stay on the author's computer. | F80: S4 How it was done (rows 17 to 20) | G80: Holds | H80: No change; when the page is rebuilt on the review's aggregates, name the new scripts in the same sentence. | K80: 0
A82: Reading the table. A verdict applies to both language versions of the page. Where a row proposes wording, it is written to be pasted; where it says "keep only after", the claim stays out of the page until the computation named is declared and run under the rules of the review (blanks as missing, no count below ten, medians and quartiles rather than extremes). The protection flags are listed again on the Open items sheet with the other matters that await the author.

Sheet By part of the chain
A1: The nine parts of the chain: what claim each one supports (the column left open in the step 3 workbook)
A2: The parts are those of the Theory of change sheet of the step 3 workbook (encampment_theory_of_change.xlsx), whose column I said "settled in step 5 of the review". Robust, Fragile and Null are the tiers of the step 4 workbook (Verdict, Shocks verdict and Indices sheets), under the rule fixed before the numbers were read: Robust when the Romano-Wolf p is at or below 0.05, the AIPW t at or above 1.96 in absolute value, the robustness value for significance at or above 0.05 and the five adjusted estimators share the sign; Null when the OLS design-based p is above 0.10 and the AIPW t below 1.96; Fragile otherwise. Figures are differences between comparable households, towns minus camp, within the common support; none is an effect of living in one place or the other. The last column counts the rows of the Verdicts sheet assigned to the part.
A4: No. | B4: Part of the chain | C4: What claim it supports | D4: Results the paper can lean on, by tier | E4: Rows of the Verdicts sheet | F4: Rows (count)
A5: 0 | B5: Before the war and where the household ended up | C5: Comparative description, with a selection model behind it. Households now in the towns differed before the war in liquidity and origin: urban origin (22% in the camp, 60% in the towns), savings in Syria (18% and 50%), own business (37% and 65%), a pension (fewer than ten camp households; 22% in the towns), less often an origin in Daraa (86% and 64%); not in recalled income (medians of 20 and 24 thousand pounds). The nine pre-war traits predict the place of residence well (area under the curve 0.87), flexible models find no interaction the logit misses (0.85 against 0.85), and six pre-war traits left out of the design barely predict it (0.56; 0.54 to 0.57 within the support with the weights). The sample over-represents households that left the camp with a sponsor. | D5: Description (step 2 and the selection model of step 4). | E5: 0.1, 0.2, 0.3, 1.1, 1.2, 1.4, 1.5, 1.6, 1.7, 3.1, 3.2, 3.3, 3.4, 4.1, 4.2, 4.9, 4.11, 4.12, M.1, M.3, M.4, M.6, M.7, M.8, M.9 | F5: =COUNTIF(Verdicts!$K$6:$K$80,A5&"") -> 25
A6: 1 | B6: What comes into the household | C6: Among comparable households, towns households name work income among their sources 24 to 30 points more often (robust under the tier rule; fragile under the eight-trait specification; 32 points before adjustment). Assistance reaches nine households in ten in both groups, as two different packages: the voucher for 93% of camp households, at JD 20 per person for nine in ten of them, and no work income among the sources for 64% of camp households; in the towns a voucher in two tiers (median JD 10 per person), cut in August 2015, UNHCR cash for 30%, and no work income for 33%. The income level itself is described (medians of JD 140 and 270 a month), not estimated. | D6: Robust: income from work (+24 points). Description: the two assistance packages. | E6: 1.3, 2.2, 2.4, 2.5, 2.6, 2.12, 4.4, 5.3, 5.6, 5.14, M.5 | F6: =COUNTIF(Verdicts!$K$6:$K$80,A6&"") -> 11
A7: 2 | B7: What the household has to pay | C7: Comparable towns households spend about 1.9 times as much per person (0.63 log points, robust). What the spending covers differs by place: rent for 87% of towns households (median JD 130) and fewer than ten camp households; food spending per person about the same (means of JD 29 and 27; medians of JD 20). Reported spending, with blanks as missing (step 5b), is food in the camp (77% of the group total; a median share of 89% among the households that report it) and rent and food in the towns (35% and 33% of the total, with electricity, water and transport behind them; education is reported by fewer than ten households). Among the 104 towns households that rent with an income and a rent reported, rent takes 44% of reported income at the median (quartiles 31% and 63%) and income after rent is JD 32 per person a month at the median (mean 35, against a mean income per person of JD 38 in the camp, where fewer than ten households pay rent); the households with the heaviest rent burden ate less and carry debt more often (nearly all of the highest third). | D7: Robust: spending per person (+0.63 log points). Description: rent, food per person, the composition of reported spending and the rent burden (step 5b). | E7: 5.2, 5.4, 5.5, 5.7 | F7: =COUNTIF(Verdicts!$K$6:$K$80,A7&"") -> 4
A8: 3 | B8: The gap | C8: About half of households in each group report spending above income (45% and 50%); among comparable households the difference (9 to 17 points) cannot be told from zero, and the sample cannot detect one below about 25 points. Debts today are more frequent among comparable towns households (12 to 22 points), a fragile difference. | D8: Null: spending above income. Fragile: debts. | E8: 4.8 | F8: =COUNTIF(Verdicts!$K$6:$K$80,A8&"") -> 1
A9: 4 | B9: How the gap is closed | C9: Fewer towns households suffered a fall in income (78% against 92%; 21 to 25 points fewer among comparable households, robust). Comparable towns households drew on savings less often (22 to 26 points, robust) and on loans less often (19 to 21 points, fragile); the consumption cuts (7 to 17 points more in the towns: eating less null, cutting other spending fragile) and the number of responses used (fragile) do not clear the tests; the severe responses (education, child work, selling) do not differ. Given the shock, among comparable households that suffered it, towns households ate less 21 points more often and cut other spending 25 points more often, drew on savings 17 points less often and on loans 20 points less, with no difference in the severe responses. Read in the order of Corbett (1988) and van der Kam (2000), from the reversible responses (eating less, borrowing, drawing on savings) to the severe ones (cutting education, child work, selling belongings), the households with the shock in the towns stayed on the reversible rungs by eating less and cutting other spending where camp households borrowed and drew on savings, and neither group went further down the ladder than the other; a description of the households with the shock. The thesis estimate of 28 points for eating less does not survive the comparison of like with like. | D9: Robust: income fell (-21), used savings (-22). Fragile: loans, cut other spending, cut education spending, worked more hours, asked another member to bring income, number of responses, financial-buffers index. Null: ate less, a child went to work, sold belongings, asked for assistance, took a second job, severe responses index, WFP score. Description: the decomposition. | E9: 1.8, 1.9, 2.3, 2.10, 2.11, 4.10, 5.1, 5.8, 5.9, 5.10, 5.11, 5.12, 5.13 | F9: =COUNTIF(Verdicts!$K$6:$K$80,A9&"") -> 13
A10: 5 | B10: Basic living conditions: refrigerator and stove | C10: More towns households have reached the two conditions: a refrigerator 30 to 40 points more often and a stove 44 to 47 points more often among comparable households, the two largest differences among the yes or no outcomes of the twelve, and both keep their tier under the eight-trait specification and the sensitivity analyses; the differences also carry the conditions of each place (electricity, space, what is provided in kind). More than nine in ten households had each good in Syria. The step to nutrition and health is supplied by other studies. | D10: Robust: refrigerator (+30 to 40), stove (+44 to 47). | E10: 2.7, 2.8, 2.9, 4.5 | F10: =COUNTIF(Verdicts!$K$6:$K$80,A10&"") -> 4
A11: 6 | B11: Security | C11: No difference among comparable households in the share rating personal security good or very good (8 points, null); camp households give more answers at both ends of the scale (very good 52% against 33%; fair or worse 29% against 14%). Theft is reported by 22% of camp households and fewer than ten in the towns (not estimated). The first contact in an emergency differs: the police for 69% in the camp and 23% in the towns, family or relatives for 22% and 51%. "No one to turn to" is not usable (blank answers counted as "no one"). | D11: Null: personal security good or very good. Description: the distribution, theft, first contact. | E11: 4.3, 4.7 | F11: =COUNTIF(Verdicts!$K$6:$K$80,A11&"") -> 2
A12: 7 | B12: Community and morale | C12: Comparable camp households rate their integration about 3.2 points higher on the 1 to 10 scale, the difference with the highest robustness value of the twelve, among men and among women alike; the answer is reported under the name of the question and read as a sense of belonging or comfort where the household lives, with the shares at 1 to 3 and 7 to 10 beside the mean. Optimism is 1.1 to 1.7 points higher in the camp, a fragile difference carried by women respondents. Happiness cannot be told apart. In the towns, households that left the camp informally, by another route or without saying how rate their integration lower than those that left with a sponsor (4.0 against 5.7). An average day, as the respondent described it (step 5b): "nothing" is the answer of 63% of camp respondents and of none in the towns, where the day is taking care of the house (45%; 53% of the women and 32% of the men who answered) or sitting in the house (31%). | D12: Robust: self-rated integration (-3.2). Fragile: optimism. Null: happiness. Description: the average day (step 5b). Not checked: the average day by employment of the respondent, by district and against the scales (5.17 to 5.19). | E12: 4.6, 5.15, 5.16, 5.17, 5.18, 5.19 | F12: =COUNTIF(Verdicts!$K$6:$K$80,A12&"") -> 6
A13: 8 | B13: Over the years in Jordan | C13: Description of households that arrived in different years (more debt in both places among earlier arrivals and, among the goods, a stove in the towns and a refrigerator in the camp; the stove in the camp does not differ); the design holds arrival by 2012 equal between the groups and the path over time is not observed. No claim about trajectories. | D13: Description only. | E13: 2.1, M.2 | F13: =COUNTIF(Verdicts!$K$6:$K$80,A13&"") -> 2
E14: Total | F14: =SUM(F5:F13) -> 68
A16: How to read the tiers in the paper. The robust set (income from work, spending per person, refrigerator, stove, self-rated integration, income fell, used savings) is what the paper can state as a difference between comparable households that holds under every test. A fragile difference (debts, optimism, loans, cut other spending, number of responses, the financial-buffers index) can be reported with the test it fails named. A null difference is reported as such, with the minimum detectable difference beside it, because the sample cannot separate a small difference from zero.

Sheet Counts
A1: Verdicts by chapter
A2: The counts by chapter and the shares are formulas over the Verdicts sheet, so a changed verdict there changes the count here; the table of the robust results at the foot carries values copied from the step 4 workbook.
A4: Chapter | B4: Holds | C4: Holds with new wording | D4: Revise | E4: Not supported | F4: Not checked | G4: All claims | H4: Protection flags | I4: Language flags
A5: Title, lead and map | B5: =COUNTIFS(Verdicts!$B$6:$B$80,"0",Verdicts!$G$6:$G$80,"Holds") -> 0 | C5: =COUNTIFS(Verdicts!$B$6:$B$80,"0",Verdicts!$G$6:$G$80,"Holds with new wording") -> 1 | D5: =COUNTIFS(Verdicts!$B$6:$B$80,"0",Verdicts!$G$6:$G$80,"Revise") -> 2 | E5: =COUNTIFS(Verdicts!$B$6:$B$80,"0",Verdicts!$G$6:$G$80,"Not supported") -> 0 | F5: =COUNTIFS(Verdicts!$B$6:$B$80,"0",Verdicts!$G$6:$G$80,"Not checked") -> 0 | G5: =COUNTIF(Verdicts!$B$6:$B$80,"0") -> 3 | H5: =COUNTIFS(Verdicts!$B$6:$B$80,"0",Verdicts!$I$6:$I$80,"<>") -> 1 | I5: =COUNTIFS(Verdicts!$B$6:$B$80,"0",Verdicts!$J$6:$J$80,"<>") -> 1
A6: Chapter 1. The households | B6: =COUNTIFS(Verdicts!$B$6:$B$80,"1",Verdicts!$G$6:$G$80,"Holds") -> 2 | C6: =COUNTIFS(Verdicts!$B$6:$B$80,"1",Verdicts!$G$6:$G$80,"Holds with new wording") -> 4 | D6: =COUNTIFS(Verdicts!$B$6:$B$80,"1",Verdicts!$G$6:$G$80,"Revise") -> 3 | E6: =COUNTIFS(Verdicts!$B$6:$B$80,"1",Verdicts!$G$6:$G$80,"Not supported") -> 0 | F6: =COUNTIFS(Verdicts!$B$6:$B$80,"1",Verdicts!$G$6:$G$80,"Not checked") -> 0 | G6: =COUNTIF(Verdicts!$B$6:$B$80,"1") -> 9 | H6: =COUNTIFS(Verdicts!$B$6:$B$80,"1",Verdicts!$I$6:$I$80,"<>") -> 2 | I6: =COUNTIFS(Verdicts!$B$6:$B$80,"1",Verdicts!$J$6:$J$80,"<>") -> 2
A7: Chapter 2. Before and after | B7: =COUNTIFS(Verdicts!$B$6:$B$80,"2",Verdicts!$G$6:$G$80,"Holds") -> 0 | C7: =COUNTIFS(Verdicts!$B$6:$B$80,"2",Verdicts!$G$6:$G$80,"Holds with new wording") -> 4 | D7: =COUNTIFS(Verdicts!$B$6:$B$80,"2",Verdicts!$G$6:$G$80,"Revise") -> 3 | E7: =COUNTIFS(Verdicts!$B$6:$B$80,"2",Verdicts!$G$6:$G$80,"Not supported") -> 2 | F7: =COUNTIFS(Verdicts!$B$6:$B$80,"2",Verdicts!$G$6:$G$80,"Not checked") -> 3 | G7: =COUNTIF(Verdicts!$B$6:$B$80,"2") -> 12 | H7: =COUNTIFS(Verdicts!$B$6:$B$80,"2",Verdicts!$I$6:$I$80,"<>") -> 1 | I7: =COUNTIFS(Verdicts!$B$6:$B$80,"2",Verdicts!$J$6:$J$80,"<>") -> 3
A8: Chapter 3. Who left the camp | B8: =COUNTIFS(Verdicts!$B$6:$B$80,"3",Verdicts!$G$6:$G$80,"Holds") -> 1 | C8: =COUNTIFS(Verdicts!$B$6:$B$80,"3",Verdicts!$G$6:$G$80,"Holds with new wording") -> 3 | D8: =COUNTIFS(Verdicts!$B$6:$B$80,"3",Verdicts!$G$6:$G$80,"Revise") -> 0 | E8: =COUNTIFS(Verdicts!$B$6:$B$80,"3",Verdicts!$G$6:$G$80,"Not supported") -> 0 | F8: =COUNTIFS(Verdicts!$B$6:$B$80,"3",Verdicts!$G$6:$G$80,"Not checked") -> 0 | G8: =COUNTIF(Verdicts!$B$6:$B$80,"3") -> 4 | H8: =COUNTIFS(Verdicts!$B$6:$B$80,"3",Verdicts!$I$6:$I$80,"<>") -> 0 | I8: =COUNTIFS(Verdicts!$B$6:$B$80,"3",Verdicts!$J$6:$J$80,"<>") -> 0
A9: Chapter 4. After adjustment | B9: =COUNTIFS(Verdicts!$B$6:$B$80,"4",Verdicts!$G$6:$G$80,"Holds") -> 0 | C9: =COUNTIFS(Verdicts!$B$6:$B$80,"4",Verdicts!$G$6:$G$80,"Holds with new wording") -> 1 | D9: =COUNTIFS(Verdicts!$B$6:$B$80,"4",Verdicts!$G$6:$G$80,"Revise") -> 9 | E9: =COUNTIFS(Verdicts!$B$6:$B$80,"4",Verdicts!$G$6:$G$80,"Not supported") -> 2 | F9: =COUNTIFS(Verdicts!$B$6:$B$80,"4",Verdicts!$G$6:$G$80,"Not checked") -> 0 | G9: =COUNTIF(Verdicts!$B$6:$B$80,"4") -> 12 | H9: =COUNTIFS(Verdicts!$B$6:$B$80,"4",Verdicts!$I$6:$I$80,"<>") -> 0 | I9: =COUNTIFS(Verdicts!$B$6:$B$80,"4",Verdicts!$J$6:$J$80,"<>") -> 1
A10: Chapter 5. Why | B10: =COUNTIFS(Verdicts!$B$6:$B$80,"5",Verdicts!$G$6:$G$80,"Holds") -> 2 | C10: =COUNTIFS(Verdicts!$B$6:$B$80,"5",Verdicts!$G$6:$G$80,"Holds with new wording") -> 6 | D10: =COUNTIFS(Verdicts!$B$6:$B$80,"5",Verdicts!$G$6:$G$80,"Revise") -> 6 | E10: =COUNTIFS(Verdicts!$B$6:$B$80,"5",Verdicts!$G$6:$G$80,"Not supported") -> 2 | F10: =COUNTIFS(Verdicts!$B$6:$B$80,"5",Verdicts!$G$6:$G$80,"Not checked") -> 3 | G10: =COUNTIF(Verdicts!$B$6:$B$80,"5") -> 19 | H10: =COUNTIFS(Verdicts!$B$6:$B$80,"5",Verdicts!$I$6:$I$80,"<>") -> 4 | I10: =COUNTIFS(Verdicts!$B$6:$B$80,"5",Verdicts!$J$6:$J$80,"<>") -> 8
A11: Data, methods and limits | B11: =COUNTIFS(Verdicts!$B$6:$B$80,"M",Verdicts!$G$6:$G$80,"Holds") -> 1 | C11: =COUNTIFS(Verdicts!$B$6:$B$80,"M",Verdicts!$G$6:$G$80,"Holds with new wording") -> 3 | D11: =COUNTIFS(Verdicts!$B$6:$B$80,"M",Verdicts!$G$6:$G$80,"Revise") -> 3 | E11: =COUNTIFS(Verdicts!$B$6:$B$80,"M",Verdicts!$G$6:$G$80,"Not supported") -> 1 | F11: =COUNTIFS(Verdicts!$B$6:$B$80,"M",Verdicts!$G$6:$G$80,"Not checked") -> 1 | G11: =COUNTIF(Verdicts!$B$6:$B$80,"M") -> 9 | H11: =COUNTIFS(Verdicts!$B$6:$B$80,"M",Verdicts!$I$6:$I$80,"<>") -> 2 | I11: =COUNTIFS(Verdicts!$B$6:$B$80,"M",Verdicts!$J$6:$J$80,"<>") -> 2
A12: All chapters | B12: =SUM(B5:B11) -> 6 | C12: =SUM(C5:C11) -> 22 | D12: =SUM(D5:D11) -> 26 | E12: =SUM(E5:E11) -> 7 | F12: =SUM(F5:F11) -> 7 | G12: =SUM(G5:G11) -> 68 | H12: =SUM(H5:H11) -> 10 | I12: =SUM(I5:I11) -> 17
A14: Share of all claims
A15: Holds | B15: =B12/$G$12 -> 0.088235294
A16: Holds with new wording | B16: =C12/$G$12 -> 0.32352941
A17: Revise | B17: =D12/$G$12 -> 0.38235294
A18: Not supported | B18: =E12/$G$12 -> 0.10294118
A19: Not checked | B19: =F12/$G$12 -> 0.10294118
A21: Check: the claims of the inventory | B21: 68 | C21: =IF(B21=G12,"equal","check") -> equal
A23: The results the paper can lean on (robust tier of the step 4 workbook)
A24: Outcome | B24: AIPW | C24: OLS | D24: Romano-Wolf p | E24: Robustness value (5%) | F24: Reading
A25: Income from work (yes or no) | B25: 0.239 | C25: 0.297 | D25: 0.008 | E25: 0.117 | F25: 24 to 30 points more frequent among comparable towns households.
A26: Monthly spending per person (log) | B26: 0.627 | C26: 0.711 | D26: 0 | E26: 0.228 | F26: About 1.9 times as much per person in the towns.
A27: Refrigerator (yes or no) | B27: 0.298 | C27: 0.396 | D27: 0 | E27: 0.256 | F27: 30 to 40 points more towns households.
A28: Stove (yes or no) | B28: 0.437 | C28: 0.472 | D28: 0 | E28: 0.279 | F28: 44 to 47 points more towns households.
A29: Self-rated integration (1 to 10) | B29: -3.189 | C29: -3.139 | D29: 0 | E29: 0.287 | F29: About 3 points higher in the camp, among men and among women.
A30: Income fell since arrival (yes or no) | B30: -0.211 | C30: -0.253 | D30: 0.001 | E30: 0.161 | F30: 21 to 25 points fewer towns households report a fall.
A31: Used savings (yes or no) | B31: -0.218 | C31: -0.261 | D31: 0.012 | E31: 0.102 | F31: 22 to 26 points fewer towns households drew on savings.
A32: Source: encampment_design_diagnostics.xlsx, Verdict and Shocks verdict sheets (design 1, within the common support; Romano-Wolf within each family of outcomes). The Romano-Wolf p of 0 means below 0.0005.

Sheet Open items
A1: Matters that await a decision of the author
A3: Item | B3: What it is and what it would take
A4: Second blind reading of the protection of households across the materials (23 October 2026) | B4: A further instance read the corrected files with the same rule, checked each item of the first reading and read anew. The origins and places passed again: every cell keeps five possible values or more. Of the items of the first reading, most were closed and some only in part, and it found new routes. Corrected the same day: in the step 4 workbook, the R2 with controls and Rmax of the rows whose raw difference is withheld, which with the classical standard error gave the variance of a yes or no outcome and so its count, now withheld; in the step 3 workbook and in this sheet, the records of the first correction, which said more than the masks they explained, rewritten; in the step 3 workbook, section 2 of the Checks sheet, whose exact shares narrowed a cross of employment and work income, now in words; in the step 2 workbook, "almost no households in Amman", now "fewer than ten". Still open, for the next edition: the scales and the household size by subgroup in the step 3 workbook (Cuts measures, For whom and Figures sheets), whose means and standard deviations, printed to four decimals with the quartiles, give back the households at some answers; until that edition the step 3 workbook is not to be uploaded. The report stays in the record of the review and does not go to the repository.
A5: Blind reading of the protection of households across the materials (23 October 2026) | B5: A separate instance read, blind, the five workbooks, the Word version of this table, the technical note, the working paper and the brief, with one task: to find any count below ten households printed, or fixed or narrowed to fewer than three values by combining printed figures, in the records of the review and in the system of origins and places of interview. The origins and places passed: every cell keeps five possible values or more. It found twelve items of substance in other figures, all corrected the same day (the second reading, in the row above, found some closed only in part). In the step 4 workbook: the standard deviations, the raw differences, the R2 without controls and the Oster quantities of the eleven responses and of sickness, which with the means given the shock of the Decomposition sheet gave the masked cells of the towns households without the shock (and, for sickness, the households outside the support), now withheld, with the weighted MDD of sickness; the index means of the Health as a factor sheet and of block C of the Decomposition sheet that gave a masked item back, now withheld wherever one of their items is masked or withheld; two cells of block C that the step 3 workbook withholds; the index rows of block A, now with two decimals; and the Blind replication sheet, which still printed some of these. In the step 3 workbook: the households where the respondent reports no employment, which with the step 1 and step 2 workbooks fixed the number of women respondents who report employment, no longer printed; and further cells withheld where a masked cell kept too few possible counts. In the step 1 workbook and a step 3 record: the size of a group of households that report assistance only, no longer printed. In this table: row 5.6 printed the share of towns households naming some assistance, which the step 2 workbook withholds; it now reads nine in ten. Low items also corrected: the brief's "almost none in Amman" (now fewer than ten), its count of the places where the earlier page broke its own rule (now the seven of row M.8, among the ten flagged claims), the description of a withheld coefficient in the step 3 workbook, and the number of possible values stated for the map (five, not six). Two differences between figures of the earlier page and the review's (rows 0.2 and 1.4) come from coding the same households and describe no trait; they are left as they are, for the author's decision. The report stays in the record of the review and does not go to the repository.
A6: Check of coherence across the materials (23 October 2026) | B6: The materials of the review were read against one another after the third reading of the brief. (1) The map of the brief printed, for the households from Damascus and Rif Dimashq in the camp, a count that differed from the 23 of the step 2 workbook: the map rested on an aggregate computed on 5 October 2026 that coded some places of origin differently. The flows were computed again on the author's computer with the coding of origin of the step 2 profile (map/m1_flujos.py; its totals by group equal those of the profile): the map now prints 211 and 23 for the two largest flows to the camp, and its lines cover 351 of the 380 households with a recorded origin (row 0.2, now Revise). Every small line, and the households off the lines at each destination and from each origin, keep five possible values or more given everything printed. (2) The loan item still read "took a loan" in the step 1 and step 3 workbooks, in two charts of step 3 and in two sentences of the step 4 workbook; it now reads "asked for a loan" everywhere, as the questionnaire asked it. (3) Protection. Some records of earlier corrections printed what they protected: the count that the map's largest flow to the towns fixed (in the technical note, the step 4 workbook and this sheet, which also printed the count of that flow), and the means and sums behind the masked cells of the consumption cuts index (step 4 workbook); they now describe each leak without its figures. The step 1 workbook printed the counts of households naming Homs and Aleppo, which with the origin counts of the step 2 workbook and the households with a recorded origin fixed the households from the other governorates at a count below ten; it now names the two places without counts. The claim column of row 5.7 printed the page's share for the highest third of the rent burden, which the row itself flags; it is now masked, and row M.8 counts it among the places where the page breaks its own rule (seven). Fourth edition of the step 1 workbook, fifth of the step 3, tenth of the step 4 and seventh of this workbook; the note, the paper and the brief carry the corrections.
A7: Third blind reading of the brief, as an interactive page (22 October 2026) | B7: Five charts of the brief were rebuilt as scrolling sequences: the text advances in steps beside a graphic that keeps its place and changes state (the map in four states, the comparison of like with like in five, the budget in three, the responses to the fall in income in five and the scales in four); the prose was redistributed into the steps with nothing cut, and the states draw only figures the page or the technical note already print (the raw shares of all households, the common support, the tiers under the eight-trait specification, the thirds of the rent burden, the causes of the fall in income, the towns means with the camp's mix of respondents). A further instance then read the interactive page blind, state by state against its text, the data tables under each sequence and the note: 43 items (2 high, 17 medium, 24 low); the reader found no leak, and the check that followed its reading found one: the count the map printed for the largest flow to the towns, which with the Daraa-origin households of Irbid governorate (68 of 90, step 3 workbook, For whom sheet) and the Ramtha total (38) fixed the Ramtha households from other governorates at a count below ten; the map now prints counts for the two largest flows to the camp only, and the convention is restated in the page, the note, the paper and the ninth edition of the step 4 workbook. The two high items were a sentence of the responses sequence that paired the raw shares of eating less and cutting other spending with the wrong groups, and the WFP severity step among the households whose income fell, which the graphic drew as significant under OLS (0.36 of a step, p 0.015) while the text said only that the step did not differ among all comparable households; both corrected, the second also in the note and the paper, which now read that row and the other response that clears the 5% line under OLS given the shock (asking another member to bring income). Also corrected: the eight-trait check shown as an annotation on the declared design rather than a recolouring of its intervals; the households set aside for a missing pre-war trait named in the support state (209 camp households with every trait observed, printed in the note); masked cells drawn as the range of values the mask allows instead of a point; the first state of the comparison counted as nine of the twelve raw differences beyond the survey margin; the map text aligned with what each state draws; two rows of the data table that printed a missing value; the Spanish page with an English mask; and the phone layout (the methods box, the reading band under the graphic). Sixth edition of this workbook; the page, the note and the paper carry the corrections. The brief is delivered in its interactive form; the author uploads it to the repository.
A8: Second blind readings of the corrected paper and of the corrected brief (22 October 2026) | B8: Two further instances read the corrected working paper and the corrected brief, each first checking the items of the first report (paper: 31 resolved, 28 partly, 8 not; brief: 33 resolved, 20 partly, 2 not) and then reading anew (28 and 35 new items). What they found was corrected in the fifth edition of this workbook, the eighth of the step 4 workbook, the fourth of the step 2 workbook, the technical note, the paper and the brief: in the Decomposition sheet of the step 4 workbook, the towns mean given the shock of the consumption cuts index, which with the mean of eating less gave back the masked item (cutting other spending) exactly, since the index is the sum of its two items, now withheld with the conditional difference of the index and the index means of the towns households without the shock; in the step 2 workbook, the count of towns households naming some assistance, which with the count naming the voucher gave the households naming assistance without the voucher, fewer than ten, now withheld; the loan item named as the questionnaire asked it (asked for a loan); the route groups of the integration cut labelled as what they are (every camp the household passed through, 83 households, not Zaatari alone); the OLS ends of the ranges of the shocks family printed in Table 5.2 of the note; the phrase "robust under every test" for income from work, which the eight-trait specification moves to fragile; the superlatives on the two goods and on integration replaced by what the record shows; the first twelve chain rows read again for places as agents, for nulls read as equalities and for ranges without both ends; and in the brief, a Spanish find-and-replace that had damaged twelve table cells, the hover texts of two charts, the navigation at desktop width and several calques. The map of the brief now prints counts for three flows (the two largest to the camp and the largest to the towns), a rule stated on the page.
A9: Blind readings of the working paper and of the brief (21 October 2026) | B9: Two further instances read, blind, the working paper (67 items) and the brief that replaces the page (55 items), each against the technical note. What they found was corrected in the fourth edition of this workbook, the seventh of the step 4 workbook, the technical note, the paper and the brief: the means and two parts of the four indices in block A of the Decomposition sheet, which with the shares of the responses gave the no-shock cells; the thesis total next to the file total, which fixed the households the thesis dropped (fewer than ten); a map count of the brief (Daraa to Ramtha) which with the Ramtha base of the integration cut gave a place-by-origin group below ten, now unlabelled; the conventions on non-response, on empty or full cells and on the map rule of five, now stated; the wording "survive every test", now "clear every test of the tier rule", since the eight-trait specification moves income from work to fragile; the ranges whose ends are the AIPW and the OLS estimates, now said; Tobin et al. (2021) cited for isolation outside the camps, now Dajani et al. (2023); the reading of Corbett (1988) and van der Kam (2000) as an ordering by reversibility rather than as a sequence of fewer buffers and deeper cuts; "education" removed from the items behind rent and food in the towns (reported by fewer than ten households); places as the subject of three sentences; the dated account of the responses in the conclusion of the paper, now a description over the whole period since arrival.
A10: Decisions of the author, 21 October 2026 | B10: The verdicts are accepted as the work to date, open to change in later iterations. Health as a factor is tested (the author's decision: no variable is left untested): done the same day as Part F of the step 4 workbook, fourth edition. The protection passes (below) were done the same day and are recorded. Fieldwork ran from June to August 2016 (row 0.3). Every programme figure on the page carries its source (row 5.8). The map keeps the rule of five households for its lines and its counts, stated on the page (row 0.2). A blank answer is a missing value, in every variable and every step: the rule is general and is not restated claim by claim.
A11: Health as a factor (Part F of the step 4 workbook, fourth edition) | B11: Run on 21 October 2026 after the author's decision, declared beforehand in review/brief_health.md and replicated blind (1,769 quantities, none to check). Among comparable households, those with a member with a medical condition used 1.3 more of the eleven responses and drew 0.54 more of the three financial buffers (both beyond the Romano-Wolf correction), with no difference in work income, spending per person or spending above income; sickness among the shocks shows no gradient of its own beyond the correction (income from work and a second job differ on their own), and three of its interactions with the place exceed their minimum detectable size (the number of responses, loans and the financial buffers index, the last beyond the correction: the camp-towns difference in the financial buffers is larger among households with sickness), a reading that rests on nearly all of the 24 towns households with sickness. The two items never enter the score, are never crossed with a town, a district or a route out of the camp, and are not used to explain the scales. For the page: health is a factor in how many responses a household had to use and how far it drew on its buffers, not in its income or spending.
A12: Step 5b: the claims marked "Not checked" that could be run under the rules | B12: Declared before running in review/brief_5b.md on 21 October 2026 and computed the same day on the author's computer (c7_presupuesto.py, aggregates out_c7.json), then replicated blind by a separate instance from the declaration alone (every value identical). Done: the composition of reported spending (5.2, 5.5), income after rent and the rent burden (5.4, 5.7), the responses by thirds of the rent burden (5.7) and the average day by group and sex of the respondent (5.16); the results are printed in the technical note (Tables 4.4 to 4.6 and 7.10) and the verdicts of this third edition rest on them. Not run, and still marked "Not checked": the average day by employment of the respondent, by district and against the scales (5.17 to 5.19), and the income conversions (2.2, 2.4, 2.5, M.5), which depend on exchange rates and on the handling of blanks and are described in the technical note, not reproduced.
A13: Second protection pass of the step 3 workbook | B13: Done on 21 October 2026 (third edition of encampment_theory_of_change.xlsx): cells are withheld, one at a time, until every masked count keeps at least three possible values given the row for all households, the other levels and the ranges behind the labels (100 cells of the Cuts sheet, 15 of them also on the For whom sheet; on 23 October 2026 further cells were withheld where a masked cell still kept too few possible counts); the type of income has two levels (with and without work income) and the indicator "assistance only" is no longer printed; the lower voucher tier of the towns also holds the households that name no voucher; the sentences that rested on a withheld cell were rewritten; the levels "no data" are the declared exception (40 cells). The step 4 workbook (fifth edition) withholds the same cells where it prints them (Shocks described, section C; Health as a factor, block B).
A14: Step 1 workbook, dollar variables, health spending and the fieldwork months | B14: Done on 21 October 2026 (third edition of encampment_variable_audit.xlsx): the counts by group of the six dollar variables and of the two questions on health spending read "not shown" and the two health questions left the audit chart; Findings No. 1 records that fieldwork ran from June to August 2016.
... A19: Thesis table | B19: The published matching table (one nearest neighbour, ATE, no support check) is reproduced within 0.0005; the page can cite it as the thesis estimate and show beside it the design 1 figures.
A21: Protection flags of the page, gathered from the Verdicts sheet
A22: Row | B22: What to correct
A23: 0.2 (Map caption) | B23: hover counts by governorate of origin to be checked in the HTML. Proposed: The caption with 351 in place of the page's figure. One check remains in the HTML of the page: the hover shows counts by governorate of origin at each destination, and a pair of five to nine households would print a count below ten; the rule agreed for the map (five or more) covers the lines drawn, and the counts shown should follow the same rule, stated on the page, or the ten rule. The brief that replaces the page shows the width class in its hover and prints counts for the two largest flows to the camp only.
A24: 1.4 (Chapter 1, unit chart (routes out of the camp)) | B24: prints a count below ten; the four counts add to the group total. Proposed: Of the 134 households in the towns, 84 passed through a camp and 50 did not. Of those 84, 42 report leaving with a Jordanian sponsor, the legal route until 2015, and the other 42 left informally, by another route, or did not say how. Households that left with a sponsor weigh more in this sample than among all exits from Zaatari.
A25: 1.6 (Chapter 1, unit chart (registration)) | B25: camp count below ten by subtraction; the twelve cut into cells below ten; the chart marks them. Proposed: The survey never asked about Ministry of Interior cards. It did ask about UNHCR registration: twelve households in the towns, and fewer than ten in the camp, reported being asylum seekers still awaiting registration; none reported being unregistered. (The ring on the chart goes, and the cut of the twelve by arrival and camp history goes with it.)
A26: 2.10 (Chapter 2, savings) | B26: a share built on counts below ten. Proposed: Half of the households later found in the towns had savings in Syria, against fewer than one in five of those in the camp; by 2016 fewer than ten households in each group reported any savings.
A27: 5.7 (Chapter 5, rent burden) | B27: The page's share for the highest third (about forty households) fixes the households that did not eat less below ten; the recount prints "nearly all".. Proposed: Among towns households that rent, rent takes 44 percent of reported income at the median, and a quarter of them pay more than 63 percent. Food cuts rise with that burden: 63 percent of households in the lowest third of the rent share ate less, and nearly all in the middle and the highest thirds; nearly all households in the highest third carry debt. This describes towns households and does not compare the two groups.
A28: 5.9 (Chapter 5, why income fell) | B28: a share whose complement is below ten. Proposed: 89 of the 103 households in the towns that gave a reason named a reduction of assistance, and nearly all of them had eaten less.
A29: 5.14 (Chapter 5, registration) | B29: two shares built on counts below ten and one with a complement below ten; a cut of twelve households. Proposed: Drop the panel and the comparison. At most one sentence: twelve households in the towns reported being still registered as asylum seekers, and none of them reported the voucher or UNHCR cash; the rules that tied assistance to registration are described in NRC and IHRC (2016).
A30: 5.18 (Chapter 5, empty days by district) | B30: district shares can reveal counts below ten. Proposed: Keep only for districts where both the respondents with an empty day and the others number ten or more; otherwise merge districts.
A31: M.6 (Methods, sample decisions) | B31: the thesis total fixes a count below ten. Proposed: All 391 households in the file (the thesis dropped fewer than ten, without recording the reason). A blank answer is treated as missing, never as zero. Spending in Syria is missing for 30 households in the towns and is reported for the camp only. The adjusted comparisons use the households with every pre-war trait observed; 48 camp households and fewer than ten in the towns are left out.
A32: M.8 (Methods, ethics and data protection) | B32: the page prints or lets a reader work out counts below ten in seven places. Proposed: Keep the paragraph; apply the seven corrections listed in this table before the page is republished, in English and in Spanish.

Sheet How it was done
A1: How it was done
A3: What this workbook is | B3: Step 5 of the review of the 2016 survey (391 households: 257 in Zaatari camp, 134 in northern towns): the verdict table. It closes the five-step plan (step 1, what the survey measures well; step 2, whom the sample represents; step 3, the theory of change; step 4, candidate designs declared before running; step 5, the verdict table).
A4: What was done | B4: 1. The text of the published page (index.html, English; the Spanish version carries the same figures) was extracted and split into claims that can be checked: a figure, a comparison, a reading or a method. Captions, chart headlines and the methods section were included; 68 claims in all. 2. The five verdict categories and the two flags were fixed before any claim was read against the review. 3. Each claim was read against the four earlier workbooks and the aggregates behind them, and the sheet that carries the evidence is named in every row. 4. For each claim a wording was proposed under the rules fixed for the review: no effect of a place, the names decided (northern towns; self-rated integration (1 to 10); basic living conditions), households as the subject of each sentence, the lexicon, and no count below ten printed or recoverable. 5. The column of the step 3 Theory of change sheet that said "settled in step 5" is settled on the By part of the chain sheet. 6. A separate instance of the AI assistant that had not written the table read every row against the cited sheets and the page before this edition (next row).
A5: Blind reading (21 October 2026) | B5: The instance checked the 67 rows of the first draft against the cited sheets, the page text, the chart, the Word document and the formulas, and found no figure of the page misquoted, no tile or count of the chart wrong and no formula wrong. What it found, all corrected in this edition: four places where this table itself let a count below ten be worked out (the route counts and the page total, the registration total, the owned-home share of the towns, the base of the savings question); figures cited to sheets that do not print them (they sit in the step 2 profile behind the sheets, now named); the WFP tiers of August 2015 stated as fact without a source read in the review (now read at the source and cited); a reading of the decomposition stated the wrong way round (the lower incidence of the shock in the towns works against the raw gap in eating less, not for it); six verdicts regraded under the definitions (1.3, 2.6, 4.5, 4.9, 4.11 and M.7 to Revise); the list of rows of part 0; two sentences wider than the sheets (the goods over the years; the replication "with none in conflict"); three claims of the page that had no row (the fieldwork months, the contacts behind the sponsor route, the hover counts of the map); and wording (places as the subject of a sentence, "nearly all" for shares the sheets print, the tier of cutting other spending, the Tamim et al. finding, Amman and Mafraq). The Word document now carries the three notes it left out.
A6: Nothing new was computed here | B6: No figure on these sheets is computed here: every number is taken from the four earlier workbooks, from the step 2 profile behind them or, in the third edition, from the step 5b aggregates (rows 5.2, 5.4, 5.5, 5.7 and 5.16), all built from aggregates copied from the author's computer and verified by checksum, with blind replications of steps 3, 4 and 5b (the only arithmetic done here is the page's own dollar rate applied to two means, in row 2.2). Claims the review did not test are marked "Not checked" with what it would take.
A7: Protection | B7: Aggregates only. The page itself prints, or lets a reader work out, counts below ten in seven places; those are masked in this table in square brackets and listed on the Open items sheet with the wording proposed. This table prints no count below ten and no pair of figures from which one could be worked out.
A8: Scripts | B8: claims_en.py (the inventory, the verdicts and the proposed wording), build_step5_table_en.py (this workbook), build_step5_chart_en.py (the chart); step 5b: c7_presupuesto.py on the author's computer (aggregates out_c7.json). The page text was extracted from the HTML with the tags removed; nothing was read from the household file to build these sheets.
A9: Second edition (21 October 2026) | B9: After the protection pass of the step 1 to 3 workbooks. Row 5.6 and the summary of part 1 no longer cite the share of camp households living on assistance alone (with the work-income count and the answering base it fixed a count below ten) and give instead the share without work income among the sources (64% in the camp and 33% in the towns); the Open items sheet records the pass as done, with what each workbook changed.
A10: Third edition (21 October 2026) | B10: After step 5b, declared in review/brief_5b.md before running and replicated blind (every value identical). Three claims leave "Not checked": the budget shares (5.2, now Holds with new wording: rent 35% and food 33% of reported spending in the towns, food 77% in the camp, blanks as missing), the rent burden and the food cuts by thirds of it (5.7, now Revise: a median of 44% of reported income, a quarter above 63%, and "nearly all" where the page printed a share for the highest third) and the average day (5.16, now Holds with new wording: 53% of the women and 32% of the men who answered in the towns take care of the house; "nothing" is the answer of 63% in the camp and of no one in the towns). Rows 5.4 and 5.5 carry the step 5b figures with their verdicts unchanged; the summaries of parts 2 and 7 and the Open items sheet record what was run and what stays unchecked (5.17 to 5.19 and the income conversions). The blind reading of the technical note (21 October 2026) also corrected, in this edition, the ranges of the loans and of the consumption cuts (AIPW to OLS throughout: loans 19 to 21 points, cutting other spending 14 to 17) and the reading of part 7 (the route levels of the third edition of step 3: 4.0 against 5.7).
A11: Seventh edition (23 October 2026) | B11: After a check of coherence across the materials of the review (Open items sheet, row of 23 October 2026). Row 0.2 moves from Holds to Revise: under the coding of origin of the step 2 profile the lines of the map cover 351 of the 380 households with a recorded origin. Row 5.7 masks the page's share for the highest third of the rent burden in its claim column, as the table does for the page's other counts below ten, and row M.8 counts it among the places where the page breaks its own rule (seven). The row on the third blind reading of the brief no longer prints the count of the map's largest flow to the towns or the count it fixed. After the blind reading of protection the same day (Open items sheet, first row), row 5.6 reads the share of towns households naming some assistance as nine in ten, since the step 2 workbook withholds it. Verdicts after this edition: Holds 6, Holds with new wording 22, Revise 26, Not supported 7, Not checked 7.
A12: Sixth edition (22 October 2026) | B12: After the third blind reading of the brief, as an interactive page (Open items sheet, row of 22 October 2026 on that reading): the sequences and what the reading found are recorded there; no verdict changes.
A13: Fifth edition (22 October 2026) | B13: After the second blind readings of the corrected paper and brief (Open items sheet, row on those readings): the summary of part 1 gives the work income range (24 to 30 points) and reads its robustness as the tier rule and the eight-trait specification give it; the summary of part 4 lists every fragile and null response of the shocks family; the summaries of parts 5 and 7 replace the superlatives on the goods and on integration by what the record shows; the notes cite the eighth edition of the step 4 workbook and the fourth of the step 2 workbook. No verdict changes.
A14: Fourth edition (22 October 2026) | B14: After the blind readings of the working paper and of the brief (Open items sheet, row on those readings of 21 October 2026): the summary of part 2 no longer lists education among the items behind rent and food in the towns (reported by fewer than ten households), the summary of part 4 reads Corbett (1988) and van der Kam (2000) as an ordering by reversibility, the summary of part 7 prints the optimism range as 1.1 to 1.7 points, and the notes cite the seventh edition of the step 4 workbook. No verdict changes.
A15: Edition | B15: 23 October 2026, seventh edition (after a check of coherence across the materials of the review and a blind reading of the protection of households the same day: row 0.2 moves to Revise and row 5.6 reads nine in ten; sixth: after the third blind reading of the brief, as an interactive page; fifth: after the second blind readings of the corrected paper and brief; fourth: after the first blind readings of the paper and the brief; third: after the blind reading, the author's decisions of 21 October, the protection pass of the step 1 to 3 workbooks and step 5b)
