Workbook

Sheet Variables
A1: No. | B1: Variable | C1: Source | D1: Block | E1: What it measures | F1: Answers for | G1: Applies to | H1: Applies: camp | I1: Applies: towns | J1: Answered: camp | K1: Answered: towns | L1: % camp | M1: % towns | N1: A blank means | O1: Verdict | P1: Why
A2: 1 | B2: id | C2: Original question | D2: 01 Identification and design | E2: Household number in the file | F2: Survey design | G2: All households | H2: 257 | I2: 134 | J2: 257 | K2: 134 | L2: =IF(AND(ISNUMBER(J2),ISNUMBER(H2)),IF(H2>0,J2/H2,""),"") -> 1 | M2: =IF(AND(ISNUMBER(K2),ISNUMBER(I2)),IF(I2>0,K2/I2,""),"") -> 1 | N2: No answer | O2: Usable | P2: Unique across the 391 households; matches the original CSV.
A3: 2 | B3: no1 | C3: Original question | D3: 01 Identification and design | E3: Running number of the interview in the northern towns | F3: Survey design | G3: Households in the northern towns | H3: 0 | I3: 134 | J3: 0 | K3: 134 | L3: =IF(AND(ISNUMBER(J3),ISNUMBER(H3)),IF(H3>0,J3/H3,""),"") | M3: =IF(AND(ISNUMBER(K3),ISNUMBER(I3)),IF(I3>0,K3/I3,""),"") -> 1 | N3: Not applicable | O3: Usable | P3: Interview order in the northern towns (1 to 134). Interviews were done place by place.
A4: 3 | B4: no2 | C4: Original question | D4: 01 Identification and design | E4: Running number of the interview in the camp | F4: Survey design | G4: Camp households | H4: 257 | I4: 0 | J4: 257 | K4: 0 | L4: =IF(AND(ISNUMBER(J4),ISNUMBER(H4)),IF(H4>0,J4/H4,""),"") -> 1 | M4: =IF(AND(ISNUMBER(K4),ISNUMBER(I4)),IF(I4>0,K4/I4,""),"") | N4: Not applicable | O4: Usable | P4: Interview order in the camp (1 to 257).
A5: 4 | B5: samplegroup | C5: Original question | D5: 01 Identification and design | E5: Group: 0 Zaatari camp, 1 northern towns (outside the camp) | F5: Survey design | G5: All households | H5: 257 | I5: 134 | J5: 257 | K5: 134 | L5: =IF(AND(ISNUMBER(J5),ISNUMBER(H5)),IF(H5>0,J5/H5,""),"") -> 1 | M5: =IF(AND(ISNUMBER(K5),ISNUMBER(I5)),IF(I5>0,K5/I5,""),"") -> 1 | N5: No answer | O5: Usable | P5: 257 camp households and 134 in the towns.
A6: 5 | B6: age | C6: Original question | D6: 02 Respondent and household | E6: Age of the respondent | F6: The respondent | G6: All households | H6: 257 | I6: 134 | J6: 257 | K6: 134 | L6: =IF(AND(ISNUMBER(J6),ISNUMBER(H6)),IF(H6>0,J6/H6,""),"") -> 1 | M6: =IF(AND(ISNUMBER(K6),ISNUMBER(I6)),IF(I6>0,K6/I6,""),"") -> 1 | N6: No answer | O6: Usable with care | P6: Complete, but it is the age of the respondent, not of the household head. Fewer than ten respondents were under 18.
A7: 6 | B7: education | C7: Original question | D7: 02 Respondent and household | E7: Schooling of the respondent (five levels) | F7: The respondent | G7: All households | H7: 257 | I7: 134 | J7: 257 | K7: 134 | L7: =IF(AND(ISNUMBER(J7),ISNUMBER(H7)),IF(H7>0,J7/H7,""),"") -> 1 | M7: =IF(AND(ISNUMBER(K7),ISNUMBER(I7)),IF(I7>0,K7/I7,""),"") -> 1 | N7: No answer | O7: Usable with care | P7: Complete, but it is the schooling of the respondent, not of the household head.
A8: 7 | B8: genderf1m2 | C8: Original question | D8: 02 Respondent and household | E8: Sex of the respondent (1 woman, 2 man) | F8: The respondent | G8: All households | H8: 257 | I8: 134 | J8: 257 | K8: 134 | L8: =IF(AND(ISNUMBER(J8),ISNUMBER(H8)),IF(H8>0,J8/H8,""),"") -> 1 | M8: =IF(AND(ISNUMBER(K8),ISNUMBER(I8)),IF(I8>0,K8/I8,""),"") -> 1 | N8: No answer | O8: Usable | P8: Complete. A woman answered in 21% of camp households and in 63% of those in the towns: this conditions every opinion question.
A9: 8 | B9: civilstatuss1m2d3w4 | C9: Original question | D9: 02 Respondent and household | E9: Marital status of the respondent (single, married, divorced, widowed) | F9: The respondent | G9: All households | H9: 257 | I9: 134 | J9: 257 | K9: 134 | L9: =IF(AND(ISNUMBER(J9),ISNUMBER(H9)),IF(H9>0,J9/H9,""),"") -> 1 | M9: =IF(AND(ISNUMBER(K9),ISNUMBER(I9)),IF(I9>0,K9/I9,""),"") -> 1 | N9: No answer | O9: Usable with care | P9: Complete; it describes the respondent. In the towns, 65 of the 84 women who answered are married: the respondent does not always head the household.
A10: 9 | B10: familysize | C10: Original question | D10: 02 Respondent and household | E10: Household size | F10: The household | G10: All households | H10: 257 | I10: 134 | J10: 257 | K10: 134 | L10: =IF(AND(ISNUMBER(J10),ISNUMBER(H10)),IF(H10>0,J10/H10,""),"") -> 1 | M10: =IF(AND(ISNUMBER(K10),ISNUMBER(I10)),IF(I10>0,K10/I10,""),"") -> 1 | N10: No answer | O10: Usable | P10: Complete. There is no household roster: the number of children is unknown.
A11: 10 | B11: medicalcondition | C11: Original question | D11: 03 Health | E11: Which household member and what condition (open answer) | F11: The household | G11: Households with a member with a medical condition | H11: 60 | I11: 51 | J11: 60 | K11: 51 | L11: =IF(AND(ISNUMBER(J11),ISNUMBER(H11)),IF(H11>0,J11/H11,""),"") -> 1 | M11: =IF(AND(ISNUMBER(K11),ISNUMBER(I11)),IF(I11>0,K11/I11,""),"") -> 1 | N11: Not applicable | O11: Protected | P11: Open answer on who has which condition. Not used.
A12: 11 | B12: medicalconditionofoneofthemember | C12: Original question | D12: 03 Health | E12: A household member has a medical condition | F12: The household | G12: All households | H12: 257 | I12: 134 | J12: 257 | K12: 134 | L12: =IF(AND(ISNUMBER(J12),ISNUMBER(H12)),IF(H12>0,J12/H12,""),"") -> 1 | M12: =IF(AND(ISNUMBER(K12),ISNUMBER(I12)),IF(I12>0,K12/I12,""),"") -> 1 | N12: No answer | O12: Usable | P12: Complete and consistent with the open answer (111 households in both). Used only as a share by group.
A13: 12 | B13: status | C13: Original question | D13: 02 Respondent and household | E13: Reported status with UNHCR: registered refugee or asylum seeker | F13: The household | G13: All households | H13: 257 | I13: 134 | J13: 257 | K13: 134 | L13: =IF(AND(ISNUMBER(J13),ISNUMBER(H13)),IF(H13>0,J13/H13,""),"") -> 1 | M13: =IF(AND(ISNUMBER(K13),ISNUMBER(I13)),IF(I13>0,K13/I13,""),"") -> 1 | N13: No answer | O13: Not usable | P13: Not enough variation: 12 households in the towns and fewer than ten in the camp reported being asylum seekers.
... A36: 35 | B36: monthsnontreatment | C36: Original question | D36: 05 Arrival and trajectory | E36: Months in the camp before leaving | F36: The household | G36: Households in the towns that passed through a camp | H36: 0 | I36: 84 | J36: 0 | K36: 28 | L36: =IF(AND(ISNUMBER(J36),ISNUMBER(H36)),IF(H36>0,J36/H36,""),"") | M36: =IF(AND(ISNUMBER(K36),ISNUMBER(I36)),IF(I36>0,K36/I36,""),"") -> 0.33333333 | N36: The duration may be in another unit (days, months or years) | O36: Usable with care | P36: Time in the camp before leaving: nearly all of the 84 households have it, most in days, 28 in months and fewer than ten in years.
A37: 36 | B37: yearsnontreatment | C37: Original question | D37: 05 Arrival and trajectory | E37: Years in the camp before leaving | F37: The household | G37: Households in the towns that passed through a camp | H37: 0 | I37: 84 | J37: 0 | K37: fewer than 10 | L37: =IF(AND(ISNUMBER(J37),ISNUMBER(H37)),IF(H37>0,J37/H37,""),"") | M37: =IF(AND(ISNUMBER(K37),ISNUMBER(I37)),IF(I37>0,K37/I37,""),"") | N37: The duration may be in another unit (days, months or years) | O37: Usable with care | P37: Time in the camp before leaving: nearly all of the 84 households have it, most in days, 28 in months and fewer than ten in years.
A38: 37 | B38: daysundertreatment | C38: Original question | D38: 05 Arrival and trajectory | E38: Days living outside the camp | F38: The household | G38: Households in the northern towns | H38: 0 | I38: 134 | J38: 0 | K38: fewer than 10 | L38: =IF(AND(ISNUMBER(J38),ISNUMBER(H38)),IF(H38>0,J38/H38,""),"") | M38: =IF(AND(ISNUMBER(K38),ISNUMBER(I38)),IF(I38>0,K38/I38,""),"") | N38: The duration may be in another unit (days, months or years) | O38: Not usable | P38: Fewer than ten answers.
A39: 38 | B39: monthsundertreatment | C39: Original question | D39: 05 Arrival and trajectory | E39: Months living outside the camp | F39: The household | G39: Households in the northern towns | H39: 0 | I39: 134 | J39: 0 | K39: fewer than 10 | L39: =IF(AND(ISNUMBER(J39),ISNUMBER(H39)),IF(H39>0,J39/H39,""),"") | M39: =IF(AND(ISNUMBER(K39),ISNUMBER(I39)),IF(I39>0,K39/I39,""),"") | N39: The duration may be in another unit (days, months or years) | O39: Not usable | P39: Fewer than ten answers.
A40: 39 | B40: yearsundertreatment | C40: Original question | D40: 05 Arrival and trajectory | E40: Years living outside the camp | F40: The household | G40: Households in the northern towns | H40: 0 | I40: 134 | J40: 0 | K40: 78 | L40: =IF(AND(ISNUMBER(J40),ISNUMBER(H40)),IF(H40>0,J40/H40,""),"") | M40: =IF(AND(ISNUMBER(K40),ISNUMBER(I40)),IF(I40>0,K40/I40,""),"") -> 0.58208955 | N40: The duration may be in another unit (days, months or years) | O40: Usable with care | P40: 78 of 134 households in the towns; for the rest only the year of arrival remains.
A41: 40 | B41: leavepermityes1no2 | C41: Original question | D41: 05 Arrival and trajectory | E41: Holds a leave permit from the camp (1 yes, 2 no) | F41: The household | G41: All households | H41: 257 | I41: 134 | J41: 248 | K41: 122 | L41: =IF(AND(ISNUMBER(J41),ISNUMBER(H41)),IF(H41>0,J41/H41,""),"") -> 0.96498054 | M41: =IF(AND(ISNUMBER(K41),ISNUMBER(I41)),IF(I41>0,K41/I41,""),"") -> 0.91044776 | N41: No answer | O41: Not usable | P41: No variation: no yes in the camp and fewer than ten in the towns.
A42: 41 | B42: housesyria | C42: Original question | D42: 07 Housing | E42: Number of dwellings of the household in Syria | F42: The household | G42: All households | H42: 257 | I42: 134 | J42: 257 | K42: 134 | L42: =IF(AND(ISNUMBER(J42),ISNUMBER(H42)),IF(H42>0,J42/H42,""),"") -> 1 | M42: =IF(AND(ISNUMBER(K42),ISNUMBER(I42)),IF(I42>0,K42/I42,""),"") -> 1 | N42: No answer | O42: Usable with care | P42: It is a count of dwellings in Syria, not a type: nearly all households had one.
A43: 42 | B43: hsownershipo1i2r3d4 | C43: Original question | D43: 07 Housing | E43: Housing tenure in Syria (O, I, R, D) | F43: The household | G43: All households | H43: 257 | I43: 134 | J43: 257 | K43: 134 | L43: =IF(AND(ISNUMBER(J43),ISNUMBER(H43)),IF(H43>0,J43/H43,""),"") -> 1 | M43: =IF(AND(ISNUMBER(K43),ISNUMBER(I43)),IF(I43>0,K43/I43,""),"") -> 1 | N43: No answer | O43: Usable | P43: Complete. 236 camp households owned their home; in the towns, nearly all.
A44: 43 | B44: hstype | C44: Original question | D44: 07 Housing | E44: Type of dwelling in Syria | F44: The household | G44: All households | H44: 257 | I44: 134 | J44: 257 | K44: 134 | L44: =IF(AND(ISNUMBER(J44),ISNUMBER(H44)),IF(H44>0,J44/H44,""),"") -> 1 | M44: =IF(AND(ISNUMBER(K44),ISNUMBER(I44)),IF(I44>0,K44/I44,""),"") -> 1 | N44: No answer | O44: Usable | P44: Complete (house or apartment).
A45: 44 | B45: housejordan | C45: Original question | D45: 07 Housing | E45: Number of dwellings of the household in Jordan (shelters or caravans in the camp) | F45: The household | G45: All households | H45: 257 | I45: 134 | J45: 257 | K45: 134 | L45: =IF(AND(ISNUMBER(J45),ISNUMBER(H45)),IF(H45>0,J45/H45,""),"") -> 1 | M45: =IF(AND(ISNUMBER(K45),ISNUMBER(I45)),IF(I45>0,K45/I45,""),"") -> 1 | N45: No answer | O45: Usable with care | P45: In the camp it counts shelters or caravans (one to five); in the towns it is always one. Usable only within the camp.
A46: 45 | B46: hjownershipo1i2r3d4 | C46: Original question | D46: 07 Housing | E46: Housing tenure in Jordan (O, I, R, D) | F46: The household | G46: All households | H46: 257 | I46: 134 | J46: 256 | K46: 134 | L46: =IF(AND(ISNUMBER(J46),ISNUMBER(H46)),IF(H46>0,J46/H46,""),"") -> 0.99610895 | M46: =IF(AND(ISNUMBER(K46),ISNUMBER(I46)),IF(I46>0,K46/I46,""),"") -> 1 | N46: No answer | O46: Usable | P46: Nearly complete. In the towns, 116 of 134 households rent; in the camp, 55 households report owning their dwelling and most of the rest a dwelling provided to them.
A47: 46 | B47: hjtype | C47: Original question | D47: 07 Housing | E47: Type of dwelling in Jordan | F47: The household | G47: All households | H47: 257 | I47: 134 | J47: 16 | K47: 132 | L47: =IF(AND(ISNUMBER(J47),ISNUMBER(H47)),IF(H47>0,J47/H47,""),"") -> 0.062256809 | M47: =IF(AND(ISNUMBER(K47),ISNUMBER(I47)),IF(I47>0,K47/I47,""),"") -> 0.98507463 | N47: No answer | O47: Usable with care | P47: Nearly complete in the towns, where nearly all live in an apartment; in the camp there are only 16 answers.
A48: 47 | B48: tvs | C48: Original question | D48: 08 Durable goods | E48: Televisions in Syria | F48: The household | G48: All households | H48: 257 | I48: 134 | J48: 257 | K48: 133 | L48: =IF(AND(ISNUMBER(J48),ISNUMBER(H48)),IF(H48>0,J48/H48,""),"") -> 1 | M48: =IF(AND(ISNUMBER(K48),ISNUMBER(I48)),IF(I48>0,K48/I48,""),"") -> 0.99253731 | N48: No answer | O48: Usable | P48: Nearly complete (257 and 133). Recalled, but concrete.
A49: 48 | B49: tvj | C49: Original question | D49: 08 Durable goods | E49: Televisions in Jordan | F49: The household | G49: All households | H49: 257 | I49: 134 | J49: 257 | K49: 133 | L49: =IF(AND(ISNUMBER(J49),ISNUMBER(H49)),IF(H49>0,J49/H49,""),"") -> 1 | M49: =IF(AND(ISNUMBER(K49),ISNUMBER(I49)),IF(I49>0,K49/I49,""),"") -> 0.99253731 | N49: No answer | O49: Usable | P49: Nearly complete (257 and 133).
A50: 49 | B50: refrigeratorss | C50: Original question | D50: 08 Durable goods | E50: Refrigerators in Syria | F50: The household | G50: All households | H50: 257 | I50: 134 | J50: 257 | K50: 133 | L50: =IF(AND(ISNUMBER(J50),ISNUMBER(H50)),IF(H50>0,J50/H50,""),"") -> 1 | M50: =IF(AND(ISNUMBER(K50),ISNUMBER(I50)),IF(I50>0,K50/I50,""),"") -> 0.99253731 | N50: No answer | O50: Usable | P50: Nearly complete (257 and 133). Recalled, but concrete.
A51: 50 | B51: refrigeratorsj | C51: Original question | D51: 08 Durable goods | E51: Refrigerators in Jordan | F51: The household | G51: All households | H51: 257 | I51: 134 | J51: 257 | K51: 133 | L51: =IF(AND(ISNUMBER(J51),ISNUMBER(H51)),IF(H51>0,J51/H51,""),"") -> 1 | M51: =IF(AND(ISNUMBER(K51),ISNUMBER(I51)),IF(I51>0,K51/I51,""),"") -> 0.99253731 | N51: No answer | O51: Usable | P51: Nearly complete (257 and 133).
... A73: 72 | B73: occupations | C73: Original question | D73: 12 Work | E73: Occupation of the respondent in Syria | F73: The respondent | G73: All households | H73: 257 | I73: 134 | J73: 244 | K73: 126 | L73: =IF(AND(ISNUMBER(J73),ISNUMBER(H73)),IF(H73>0,J73/H73,""),"") -> 0.94941634 | M73: =IF(AND(ISNUMBER(K73),ISNUMBER(I73)),IF(I73>0,K73/I73,""),"") -> 0.94029851 | N73: No answer | O73: Usable with care | P73: Occupation of the respondent in Syria, in 48 distinct texts.
A74: 73 | B74: occupationsfather | C74: Original question | D74: 12 Work | E74: Occupation of the father in Syria, when another person answered | F74: The father or the mother | G74: Only where applicable | J74: 27 | K74: 22 | L74: =IF(AND(ISNUMBER(J74),ISNUMBER(H74)),IF(H74>0,J74/H74,""),"") | M74: =IF(AND(ISNUMBER(K74),ISNUMBER(I74)),IF(I74>0,K74/I74,""),"") | N74: Cannot be known | O74: Not usable | P74: 49 answers: filled in only when another household member answered.
A75: 74 | B75: occupationj | C75: Original question | D75: 12 Work | E75: Occupation of the respondent in Jordan | F75: The respondent | G75: All households | H75: 257 | I75: 134 | J75: 249 | K75: 126 | L75: =IF(AND(ISNUMBER(J75),ISNUMBER(H75)),IF(H75>0,J75/H75,""),"") -> 0.9688716 | M75: =IF(AND(ISNUMBER(K75),ISNUMBER(I75)),IF(I75>0,K75/I75,""),"") -> 0.94029851 | N75: No answer | O75: Usable with care | P75: Occupation of the respondent in Jordan, in 33 texts; includes housewife and no work.
A76: 75 | B76: occupationjfather | C76: Original question | D76: 12 Work | E76: Occupation of the father in Jordan, when another person answered | F76: The father or the mother | G76: Only where applicable | J76: 23 | K76: 22 | L76: =IF(AND(ISNUMBER(J76),ISNUMBER(H76)),IF(H76>0,J76/H76,""),"") | M76: =IF(AND(ISNUMBER(K76),ISNUMBER(I76)),IF(I76>0,K76/I76,""),"") | N76: Cannot be known | O76: Not usable | P76: 45 answers; it enters only combined in JobHHHJordan.
A77: 76 | B77: psourceins | C77: Original question | D77: 13 Income by source | E77: Main source of income in Syria | F77: The household | G77: All households | H77: 257 | I77: 134 | J77: 254 | K77: 131 | L77: =IF(AND(ISNUMBER(J77),ISNUMBER(H77)),IF(H77>0,J77/H77,""),"") -> 0.98832685 | M77: =IF(AND(ISNUMBER(K77),ISNUMBER(I77)),IF(I77>0,K77/I77,""),"") -> 0.97761194 | N77: No answer | O77: Usable | P77: 254 and 131 answers. The father's work is the main source in 320 households.
A78: 77 | B78: psourceinsamount | C78: Original question | D78: 13 Income by source | E78: Monthly amount of the main source in Syria | F78: The household | G78: All households | H78: 257 | I78: 134 | J78: 253 | K78: 115 | L78: =IF(AND(ISNUMBER(J78),ISNUMBER(H78)),IF(H78>0,J78/H78,""),"") -> 0.9844358 | M78: =IF(AND(ISNUMBER(K78),ISNUMBER(I78)),IF(I78>0,K78/I78,""),"") -> 0.85820896 | N78: No answer | O78: Usable with care | P78: Recalled amount in Syrian pounds. In the towns, 115 of 134 households gave it; 16 name the source without the amount.
A79: 78 | B79: ssourceins | C79: Original question | D79: 13 Income by source | E79: Second source of income in Syria | F79: The household | G79: Only where applicable | J79: fewer than 10 | K79: 16 | L79: =IF(AND(ISNUMBER(J79),ISNUMBER(H79)),IF(H79>0,J79/H79,""),"") | M79: =IF(AND(ISNUMBER(K79),ISNUMBER(I79)),IF(I79>0,K79/I79,""),"") | N79: Not applicable | O79: Not usable | P79: Fewer than 30 households report a second source in Syria.
A80: 79 | B80: ssourceinsamount | C80: Original question | D80: 13 Income by source | E80: Monthly amount of the second source in Syria | F80: The household | G80: Only where applicable | J80: fewer than 10 | K80: 15 | L80: =IF(AND(ISNUMBER(J80),ISNUMBER(H80)),IF(H80>0,J80/H80,""),"") | M80: =IF(AND(ISNUMBER(K80),ISNUMBER(I80)),IF(I80>0,K80/I80,""),"") | N80: Not applicable | O80: Not usable | P80: Fewer than 30 households report a second source in Syria.
A81: 80 | B81: tsourceins | C81: Original question | D81: 13 Income by source | E81: Third source of income in Syria | F81: The household | G81: Only where applicable | J81: 0 | K81: fewer than 10 | L81: =IF(AND(ISNUMBER(J81),ISNUMBER(H81)),IF(H81>0,J81/H81,""),"") | M81: =IF(AND(ISNUMBER(K81),ISNUMBER(I81)),IF(I81>0,K81/I81,""),"") | N81: Not applicable | O81: Not usable | P81: Fewer than ten households.
A82: 81 | B82: tsourceinsamount | C82: Original question | D82: 13 Income by source | E82: Monthly amount of the third source in Syria | F82: The household | G82: Only where applicable | J82: 0 | K82: fewer than 10 | L82: =IF(AND(ISNUMBER(J82),ISNUMBER(H82)),IF(H82>0,J82/H82,""),"") | M82: =IF(AND(ISNUMBER(K82),ISNUMBER(I82)),IF(I82>0,K82/I82,""),"") | N82: Not applicable | O82: Not usable | P82: Fewer than ten households.
A83: 82 | B83: psourceinj | C83: Original question | D83: 13 Income by source | E83: Main source of income in Jordan | F83: The household | G83: All households | H83: 257 | I83: 134 | J83: 248 | K83: 132 | L83: =IF(AND(ISNUMBER(J83),ISNUMBER(H83)),IF(H83>0,J83/H83,""),"") -> 0.96498054 | M83: =IF(AND(ISNUMBER(K83),ISNUMBER(I83)),IF(I83>0,K83/I83,""),"") -> 0.98507463 | N83: No answer | O83: Usable | P83: 248 and 132 answers. It separates WFP vouchers, UNHCR cash, work and help from relatives.
A84: 83 | B84: psourceinjamount | C84: Original question | D84: 13 Income by source | E84: Monthly amount of the main source in Jordan | F84: The household | G84: All households | H84: 257 | I84: 134 | J84: 248 | K84: 129 | L84: =IF(AND(ISNUMBER(J84),ISNUMBER(H84)),IF(H84>0,J84/H84,""),"") -> 0.96498054 | M84: =IF(AND(ISNUMBER(K84),ISNUMBER(I84)),IF(I84>0,K84/I84,""),"") -> 0.96268657 | N84: No answer | O84: Usable | P84: 248 and 129 answers. In about nine in ten camp households that report assistance only, the amount matches the official voucher, JD 20 (Jordanian dinars) per person (a6_vale_solo_asistencia.py).
A85: 84 | B85: ssourceinj | C85: Original question | D85: 13 Income by source | E85: Second source of income in Jordan | F85: The household | G85: Only where applicable | J85: 79 | K85: 116 | L85: =IF(AND(ISNUMBER(J85),ISNUMBER(H85)),IF(H85>0,J85/H85,""),"") | M85: =IF(AND(ISNUMBER(K85),ISNUMBER(I85)),IF(I85>0,K85/I85,""),"") | N85: Not applicable | O85: Usable | P85: 79 camp households and 116 in the towns report a second source; a blank means not having one.
A86: 85 | B86: ssourceinjamount | C86: Original question | D86: 13 Income by source | E86: Monthly amount of the second source in Jordan | F86: The household | G86: Only where applicable | J86: 79 | K86: 112 | L86: =IF(AND(ISNUMBER(J86),ISNUMBER(H86)),IF(H86>0,J86/H86,""),"") | M86: =IF(AND(ISNUMBER(K86),ISNUMBER(I86)),IF(I86>0,K86/I86,""),"") | N86: Not applicable | O86: Usable | P86: 79 and 112 answers.
A87: 86 | B87: tsourceinj | C87: Original question | D87: 13 Income by source | E87: Third source of income in Jordan | F87: The household | G87: Only where applicable | J87: fewer than 10 | K87: 25 | L87: =IF(AND(ISNUMBER(J87),ISNUMBER(H87)),IF(H87>0,J87/H87,""),"") | M87: =IF(AND(ISNUMBER(K87),ISNUMBER(I87)),IF(I87>0,K87/I87,""),"") | N87: Not applicable | O87: Usable with care | P87: Fewer than ten camp households and 25 in the towns report a third source.
A88: 87 | B88: tsourceinjamount | C88: Original question | D88: 13 Income by source | E88: Monthly amount of the third source in Jordan | F88: The household | G88: Only where applicable | J88: fewer than 10 | K88: 20 | L88: =IF(AND(ISNUMBER(J88),ISNUMBER(H88)),IF(H88>0,J88/H88,""),"") | M88: =IF(AND(ISNUMBER(K88),ISNUMBER(I88)),IF(I88>0,K88/I88,""),"") | N88: Not applicable | O88: Usable with care | P88: Fewer than ten camp households and 20 in the towns.
A89: 88 | B89: rents | C89: Original question | D89: 14 Spending by item | E89: Monthly rent in Syria | F89: The household | G89: All households | H89: 257 | I89: 134 | J89: fewer than 10 | K89: fewer than 10 | L89: =IF(AND(ISNUMBER(J89),ISNUMBER(H89)),IF(H89>0,J89/H89,""),"") | M89: =IF(AND(ISNUMBER(K89),ISNUMBER(I89)),IF(I89>0,K89/I89,""),"") | N89: Zero or no answer (cannot be told apart) | O89: Not usable | P89: Fewer than ten answers per group: nearly all households owned their home.
A90: 89 | B90: rentj | C90: Original question | D90: 14 Spending by item | E90: Monthly rent in Jordan | F90: The household | G90: Households that rent | H90: fewer than 10 | I90: 116 | J90: fewer than 10 | K90: 105 | L90: =IF(AND(ISNUMBER(J90),ISNUMBER(H90)),IF(H90>0,J90/H90,""),"") | M90: =IF(AND(ISNUMBER(K90),ISNUMBER(I90)),IF(I90>0,K90/I90,""),"") -> 0.90517241 | N90: No answer | O90: Usable | P90: Given by 105 of the 116 households that rent in the towns.
A91: 90 | B91: foods | C91: Original question | D91: 14 Spending by item | E91: Monthly spending on food in Syria | F91: The household | G91: All households | H91: 257 | I91: 134 | J91: 248 | K91: 64 | L91: =IF(AND(ISNUMBER(J91),ISNUMBER(H91)),IF(H91>0,J91/H91,""),"") -> 0.96498054 | M91: =IF(AND(ISNUMBER(K91),ISNUMBER(I91)),IF(I91>0,K91/I91,""),"") -> 0.47761194 | N91: No answer | O91: Usable with care | P91: 248 camp households, but only 64 of 134 in the towns.
A92: 91 | B92: foodj | C92: Original question | D92: 14 Spending by item | E92: Monthly spending on food in Jordan | F92: The household | G92: All households | H92: 257 | I92: 134 | J92: 221 | K92: 106 | L92: =IF(AND(ISNUMBER(J92),ISNUMBER(H92)),IF(H92>0,J92/H92,""),"") -> 0.85992218 | M92: =IF(AND(ISNUMBER(K92),ISNUMBER(I92)),IF(I92>0,K92/I92,""),"") -> 0.79104478 | N92: No answer | O92: Usable with care | P92: 221 and 106 answers; 36 camp households and 28 in the towns are missing.
A93: 92 | B93: healths | C93: Original question | D93: 14 Spending by item | E93: Monthly spending on health in Syria | F93: The household | G93: All households | H93: 257 | I93: 134 | J93: not shown | K93: not shown | L93: =IF(AND(ISNUMBER(J93),ISNUMBER(H93)),IF(H93>0,J93/H93,""),"") | M93: =IF(AND(ISNUMBER(K93),ISNUMBER(I93)),IF(I93>0,K93/I93,""),"") | N93: Zero or no answer (cannot be told apart) | O93: Not usable | P93: Fewer than a third of households wrote an amount; a blank may be zero or no answer. The counts by group are not shown: health questions are not crossed with place (How it was done sheet, protection of households).
A94: 93 | B94: healthj | C94: Original question | D94: 14 Spending by item | E94: Monthly spending on health in Jordan | F94: The household | G94: All households | H94: 257 | I94: 134 | J94: not shown | K94: not shown | L94: =IF(AND(ISNUMBER(J94),ISNUMBER(H94)),IF(H94>0,J94/H94,""),"") | M94: =IF(AND(ISNUMBER(K94),ISNUMBER(I94)),IF(I94>0,K94/I94,""),"") | N94: Zero or no answer (cannot be told apart) | O94: Not usable | P94: Fewer than a quarter of households wrote an amount; a blank may be zero or no answer. The counts by group are not shown: health questions are not crossed with place (How it was done sheet, protection of households).
A95: 94 | B95: educations | C95: Original question | D95: 14 Spending by item | E95: Monthly spending on education in Syria | F95: The household | G95: All households | H95: 257 | I95: 134 | J95: 33 | K95: fewer than 10 | L95: =IF(AND(ISNUMBER(J95),ISNUMBER(H95)),IF(H95>0,J95/H95,""),"") -> 0.12840467 | M95: =IF(AND(ISNUMBER(K95),ISNUMBER(I95)),IF(I95>0,K95/I95,""),"") | N95: Zero or no answer (cannot be told apart) | O95: Not usable | P95: 33 camp households and fewer than ten in the towns.
A96: 95 | B96: educationj | C96: Original question | D96: 14 Spending by item | E96: Monthly spending on education in Jordan | F96: The household | G96: All households | H96: 257 | I96: 134 | J96: fewer than 10 | K96: 10 | L96: =IF(AND(ISNUMBER(J96),ISNUMBER(H96)),IF(H96>0,J96/H96,""),"") | M96: =IF(AND(ISNUMBER(K96),ISNUMBER(I96)),IF(I96>0,K96/I96,""),"") -> 0.074626866 | N96: Zero or no answer (cannot be told apart) | O96: Not usable | P96: Fewer than ten camp households and 10 in the towns.
A97: 96 | B97: electricitys | C97: Original question | D97: 14 Spending by item | E97: Monthly spending on electricity in Syria | F97: The household | G97: All households | H97: 257 | I97: 134 | J97: 247 | K97: 90 | L97: =IF(AND(ISNUMBER(J97),ISNUMBER(H97)),IF(H97>0,J97/H97,""),"") -> 0.96108949 | M97: =IF(AND(ISNUMBER(K97),ISNUMBER(I97)),IF(I97>0,K97/I97,""),"") -> 0.67164179 | N97: Zero or no answer (cannot be told apart) | O97: Usable with care | P97: 247 camp households and 90 in the towns.
A98: 97 | B98: electricityj | C98: Original question | D98: 14 Spending by item | E98: Monthly spending on electricity in Jordan | F98: The household | G98: All households | H98: 257 | I98: 134 | J98: fewer than 10 | K98: 115 | L98: =IF(AND(ISNUMBER(J98),ISNUMBER(H98)),IF(H98>0,J98/H98,""),"") | M98: =IF(AND(ISNUMBER(K98),ISNUMBER(I98)),IF(I98>0,K98/I98,""),"") -> 0.85820896 | N98: Zero or no answer (cannot be told apart) | O98: Usable with care | P98: In the towns, 115 of 134 households; in the camp almost nobody pays for electricity.
A99: 98 | B99: waters | C99: Original question | D99: 14 Spending by item | E99: Monthly spending on water in Syria | F99: The household | G99: All households | H99: 257 | I99: 134 | J99: 237 | K99: 65 | L99: =IF(AND(ISNUMBER(J99),ISNUMBER(H99)),IF(H99>0,J99/H99,""),"") -> 0.92217899 | M99: =IF(AND(ISNUMBER(K99),ISNUMBER(I99)),IF(I99>0,K99/I99,""),"") -> 0.48507463 | N99: Zero or no answer (cannot be told apart) | O99: Usable with care | P99: 237 camp households and 65 in the towns.
A100: 99 | B100: waterj | C100: Original question | D100: 14 Spending by item | E100: Monthly spending on water in Jordan | F100: The household | G100: All households | H100: 257 | I100: 134 | J100: fewer than 10 | K100: 101 | L100: =IF(AND(ISNUMBER(J100),ISNUMBER(H100)),IF(H100>0,J100/H100,""),"") | M100: =IF(AND(ISNUMBER(K100),ISNUMBER(I100)),IF(I100>0,K100/I100,""),"") -> 0.75373134 | N100: Zero or no answer (cannot be told apart) | O100: Usable with care | P100: In the towns, 101 of 134 households; in the camp almost nobody pays for piped water.
A101: 100 | B101: drinkablews | C101: Original question | D101: 14 Spending by item | E101: Monthly spending on drinking water in Syria | F101: The household | G101: All households | H101: 257 | I101: 134 | J101: 15 | K101: fewer than 10 | L101: =IF(AND(ISNUMBER(J101),ISNUMBER(H101)),IF(H101>0,J101/H101,""),"") -> 0.058365759 | M101: =IF(AND(ISNUMBER(K101),ISNUMBER(I101)),IF(I101>0,K101/I101,""),"") | N101: Zero or no answer (cannot be told apart) | O101: Not usable | P101: 15 camp households and fewer than ten in the towns.
A102: 101 | B102: drinkablewj | C102: Original question | D102: 14 Spending by item | E102: Monthly spending on drinking water in Jordan | F102: The household | G102: All households | H102: 257 | I102: 134 | J102: 177 | K102: 113 | L102: =IF(AND(ISNUMBER(J102),ISNUMBER(H102)),IF(H102>0,J102/H102,""),"") -> 0.68871595 | M102: =IF(AND(ISNUMBER(K102),ISNUMBER(I102)),IF(I102>0,K102/I102,""),"") -> 0.84328358 | N102: Zero or no answer (cannot be told apart) | O102: Usable with care | P102: 177 and 113 answers. Fewer than ten out-of-range values.
A103: 102 | B103: transportations | C103: Original question | D103: 14 Spending by item | E103: Monthly spending on transport in Syria | F103: The household | G103: All households | H103: 257 | I103: 134 | J103: 64 | K103: 12 | L103: =IF(AND(ISNUMBER(J103),ISNUMBER(H103)),IF(H103>0,J103/H103,""),"") -> 0.24902724 | M103: =IF(AND(ISNUMBER(K103),ISNUMBER(I103)),IF(I103>0,K103/I103,""),"") -> 0.089552239 | N103: Zero or no answer (cannot be told apart) | O103: Not usable | P103: 64 and 12 answers. A blank may be zero or no answer.
A104: 103 | B104: transportationsj | C104: Original question | D104: 14 Spending by item | E104: Monthly spending on transport in Jordan | F104: The household | G104: All households | H104: 257 | I104: 134 | J104: 36 | K104: 44 | L104: =IF(AND(ISNUMBER(J104),ISNUMBER(H104)),IF(H104>0,J104/H104,""),"") -> 0.14007782 | M104: =IF(AND(ISNUMBER(K104),ISNUMBER(I104)),IF(I104>0,K104/I104,""),"") -> 0.32835821 | N104: Zero or no answer (cannot be told apart) | O104: Not usable | P104: 36 and 44 answers. A blank may be zero or no answer.
A105: 104 | B105: otherexs | C105: Original question | D105: 14 Spending by item | E105: Other monthly spending in Syria | F105: The household | G105: All households | H105: 257 | I105: 134 | J105: 22 | K105: fewer than 10 | L105: =IF(AND(ISNUMBER(J105),ISNUMBER(H105)),IF(H105>0,J105/H105,""),"") -> 0.085603113 | M105: =IF(AND(ISNUMBER(K105),ISNUMBER(I105)),IF(I105>0,K105/I105,""),"") | N105: Zero or no answer (cannot be told apart) | O105: Not usable | P105: 22 camp households and fewer than ten in the towns.
A106: 105 | B106: otherexj | C106: Original question | D106: 14 Spending by item | E106: Other monthly spending in Jordan | F106: The household | G106: All households | H106: 257 | I106: 134 | J106: 24 | K106: 30 | L106: =IF(AND(ISNUMBER(J106),ISNUMBER(H106)),IF(H106>0,J106/H106,""),"") -> 0.093385214 | M106: =IF(AND(ISNUMBER(K106),ISNUMBER(I106)),IF(I106>0,K106/I106,""),"") -> 0.2238806 | N106: Zero or no answer (cannot be told apart) | O106: Not usable | P106: 24 and 30 answers.
A107: 106 | B107: totalexs | C107: Original question | D107: 14 Spending by item | E107: Total monthly spending in Syria | F107: The household | G107: All households | H107: 257 | I107: 134 | J107: 252 | K107: 95 | L107: =IF(AND(ISNUMBER(J107),ISNUMBER(H107)),IF(H107>0,J107/H107,""),"") -> 0.98054475 | M107: =IF(AND(ISNUMBER(K107),ISNUMBER(I107)),IF(I107>0,K107/I107,""),"") -> 0.70895522 | N107: No answer | O107: Usable with care | P107: 252 camp households and 95 in the towns. It is the sum of the items answered.
A108: 107 | B108: totalexj | C108: Original question | D108: 14 Spending by item | E108: Total monthly spending in Jordan | F108: The household | G108: All households | H108: 257 | I108: 134 | J108: 239 | K108: 121 | L108: =IF(AND(ISNUMBER(J108),ISNUMBER(H108)),IF(H108>0,J108/H108,""),"") -> 0.92996109 | M108: =IF(AND(ISNUMBER(K108),ISNUMBER(I108)),IF(I108>0,K108/I108,""),"") -> 0.90298507 | N108: No answer | O108: Usable with care | P108: 239 and 121 answers. It adds items whose blanks may be zero, and it exceeds reported income in 45% of camp households and 50% of those in the towns.
A109: 108 | B109: informals | C109: Original question | D109: 12 Work | E109: Informal work in Syria | F109: Unclear | G109: All households | H109: 257 | I109: 134 | J109: 257 | K109: 133 | L109: =IF(AND(ISNUMBER(J109),ISNUMBER(H109)),IF(H109>0,J109/H109,""),"") -> 1 | M109: =IF(AND(ISNUMBER(K109),ISNUMBER(I109)),IF(I109>0,K109/I109,""),"") -> 0.99253731 | N109: No answer | O109: Usable with care | P109: Nearly complete, but it is unclear whether it describes the respondent or the household head.
A110: 109 | B110: informalj | C110: Original question | D110: 12 Work | E110: Informal work in Jordan | F110: Unclear | G110: All households | H110: 257 | I110: 134 | J110: 257 | K110: 133 | L110: =IF(AND(ISNUMBER(J110),ISNUMBER(H110)),IF(H110>0,J110/H110,""),"") -> 1 | M110: =IF(AND(ISNUMBER(K110),ISNUMBER(I110)),IF(I110>0,K110/I110,""),"") -> 0.99253731 | N110: No answer | O110: Usable with care | P110: Nearly complete, but it is unclear whether it describes the respondent or the household head.
A111: 110 | B111: businesss | C111: Original question | D111: 12 Work | E111: Own business in Syria | F111: The household | G111: All households | H111: 257 | I111: 134 | J111: 257 | K111: 133 | L111: =IF(AND(ISNUMBER(J111),ISNUMBER(H111)),IF(H111>0,J111/H111,""),"") -> 1 | M111: =IF(AND(ISNUMBER(K111),ISNUMBER(I111)),IF(I111>0,K111/I111,""),"") -> 0.99253731 | N111: No answer | O111: Usable | P111: Nearly complete (257 and 133).
A112: 111 | B112: businessj | C112: Original question | D112: 12 Work | E112: Own business in Jordan | F112: The household | G112: All households | H112: 257 | I112: 134 | J112: 257 | K112: 133 | L112: =IF(AND(ISNUMBER(J112),ISNUMBER(H112)),IF(H112>0,J112/H112,""),"") -> 1 | M112: =IF(AND(ISNUMBER(K112),ISNUMBER(I112)),IF(I112>0,K112/I112,""),"") -> 0.99253731 | N112: No answer | O112: Usable | P112: Nearly complete (257 and 133).
A113: 112 | B113: morethanoneattimes | C113: Original question | D113: 12 Work | E113: More than one job at a time in Syria | F113: Unclear | G113: All households | H113: 257 | I113: 134 | J113: 257 | K113: 130 | L113: =IF(AND(ISNUMBER(J113),ISNUMBER(H113)),IF(H113>0,J113/H113,""),"") -> 1 | M113: =IF(AND(ISNUMBER(K113),ISNUMBER(I113)),IF(I113>0,K113/I113,""),"") -> 0.97014925 | N113: No answer | O113: Usable with care | P113: Nearly complete, but it is unclear whether it describes the respondent or the household head.
A114: 113 | B114: morethanoneattimej | C114: Original question | D114: 12 Work | E114: More than one job at a time in Jordan | F114: Unclear | G114: All households | H114: 257 | I114: 134 | J114: 256 | K114: 133 | L114: =IF(AND(ISNUMBER(J114),ISNUMBER(H114)),IF(H114>0,J114/H114,""),"") -> 0.99610895 | M114: =IF(AND(ISNUMBER(K114),ISNUMBER(I114)),IF(I114>0,K114/I114,""),"") -> 0.99253731 | N114: No answer | O114: Usable with care | P114: Nearly complete, but it is unclear whether it describes the respondent or the household head.
A115: 114 | B115: workingtimes | C115: Original question | D115: 12 Work | E115: Working hours in Syria | F115: Unclear | G115: Only where applicable | J115: 216 | K115: 75 | L115: =IF(AND(ISNUMBER(J115),ISNUMBER(H115)),IF(H115>0,J115/H115,""),"") | M115: =IF(AND(ISNUMBER(K115),ISNUMBER(I115)),IF(I115>0,K115/I115,""),"") | N115: Not applicable | O115: Usable with care | P115: 216 and 75 answers; it is unclear whose hours they are.
A116: 115 | B116: workingtimej | C116: Original question | D116: 12 Work | E116: Working hours in Jordan | F116: Unclear | G116: Only where applicable | J116: 64 | K116: 57 | L116: =IF(AND(ISNUMBER(J116),ISNUMBER(H116)),IF(H116>0,J116/H116,""),"") | M116: =IF(AND(ISNUMBER(K116),ISNUMBER(I116)),IF(I116>0,K116/I116,""),"") | N116: Not applicable | O116: Usable with care | P116: 64 and 57 answers. 56 come from respondents recorded as not employed, so the hours belong to another household member.
A117: 116 | B117: satisfactionworks | C117: Original question | D117: 12 Work | E117: Satisfaction with work in Syria (four levels) | F117: The respondent | G117: All households | H117: 257 | I117: 134 | J117: 247 | K117: 124 | L117: =IF(AND(ISNUMBER(J117),ISNUMBER(H117)),IF(H117>0,J117/H117,""),"") -> 0.96108949 | M117: =IF(AND(ISNUMBER(K117),ISNUMBER(I117)),IF(I117>0,K117/I117,""),"") -> 0.92537313 | N117: No answer | O117: Usable with care | P117: 247 and 124 answers; those who were not working answered it too.
A118: 117 | B118: satisfactionworkj | C118: Original question | D118: 12 Work | E118: Satisfaction with work in Jordan (four levels) | F118: The respondent | G118: All households | H118: 257 | I118: 134 | J118: 243 | K118: 116 | L118: =IF(AND(ISNUMBER(J118),ISNUMBER(H118)),IF(H118>0,J118/H118,""),"") -> 0.94552529 | M118: =IF(AND(ISNUMBER(K118),ISNUMBER(I118)),IF(I118>0,K118/I118,""),"") -> 0.86567164 | N118: No answer | O118: Usable with care | P118: 243 and 116 answers; those who are not working answer it too, so it measures satisfaction with work opportunities.
A119: 118 | B119: happiness | C119: Original question | D119: 15 Wellbeing | E119: Happiness (1 to 10) | F119: The respondent | G119: All households | H119: 257 | I119: 134 | J119: 257 | K119: 132 | L119: =IF(AND(ISNUMBER(J119),ISNUMBER(H119)),IF(H119>0,J119/H119,""),"") -> 1 | M119: =IF(AND(ISNUMBER(K119),ISNUMBER(I119)),IF(I119>0,K119/I119,""),"") -> 0.98507463 | N119: No answer | O119: Usable with care | P119: Nearly complete. It is a single question from 1 to 10 and depends on who answered.
A120: 119 | B120: optimism | C120: Original question | D120: 15 Wellbeing | E120: Optimism about the future (1 to 10) | F120: The respondent | G120: All households | H120: 257 | I120: 134 | J120: 257 | K120: 133 | L120: =IF(AND(ISNUMBER(J120),ISNUMBER(H120)),IF(H120>0,J120/H120,""),"") -> 1 | M120: =IF(AND(ISNUMBER(K120),ISNUMBER(I120)),IF(I120>0,K120/I120,""),"") -> 0.99253731 | N120: No answer | O120: Usable with care | P120: Nearly complete. It is a single question from 1 to 10 and depends on who answered; in the towns, 27% answered 1.
A121: 120 | B121: securityfamily | C121: Original question | D121: 16 Security and whom to turn to | E121: Security of the family (1 to 5) | F121: The respondent | G121: All households | H121: 257 | I121: 134 | J121: 256 | K121: 133 | L121: =IF(AND(ISNUMBER(J121),ISNUMBER(H121)),IF(H121>0,J121/H121,""),"") -> 0.99610895 | M121: =IF(AND(ISNUMBER(K121),ISNUMBER(I121)),IF(I121>0,K121/I121,""),"") -> 0.99253731 | N121: No answer | O121: Usable with care | P121: Recorded as a number in the camp and as a word in the towns (133 households): the format changes between groups.
A122: 121 | B122: emergency1family | C122: Original question | D122: 16 Security and whom to turn to | E122: First contact in a family emergency | F122: The respondent | G122: All households | H122: 257 | I122: 134 | J122: 256 | K122: 116 | L122: =IF(AND(ISNUMBER(J122),ISNUMBER(H122)),IF(H122>0,J122/H122,""),"") -> 0.99610895 | M122: =IF(AND(ISNUMBER(K122),ISNUMBER(I122)),IF(I122>0,K122/I122,""),"") -> 0.86567164 | N122: Cannot be known | O122: Usable with care | P122: 256 and 116 answers. It nearly always repeats the contact of the personal question (230 of 256 camp households).
A123: 122 | B123: emergency2family | C123: Original question | D123: 16 Security and whom to turn to | E123: Second contact in a family emergency | F123: The respondent | G123: Only where applicable | J123: 215 | K123: 54 | L123: =IF(AND(ISNUMBER(J123),ISNUMBER(H123)),IF(H123>0,J123/H123,""),"") | M123: =IF(AND(ISNUMBER(K123),ISNUMBER(I123)),IF(I123>0,K123/I123,""),"") | N123: Not applicable | O123: Usable with care | P123: Second contact: 215 and 54 answers.
A124: 123 | B124: emergency3family | C124: Original question | D124: 16 Security and whom to turn to | E124: Third contact in a family emergency | F124: The respondent | G124: Only where applicable | J124: 164 | K124: fewer than 10 | L124: =IF(AND(ISNUMBER(J124),ISNUMBER(H124)),IF(H124>0,J124/H124,""),"") | M124: =IF(AND(ISNUMBER(K124),ISNUMBER(I124)),IF(I124>0,K124/I124,""),"") | N124: Not applicable | O124: Usable with care | P124: Third contact: 164 camp households and fewer than ten in the towns.
A125: 124 | B125: security | C125: Original question | D125: 16 Security and whom to turn to | E125: Personal security (1 to 5) | F125: The respondent | G125: All households | H125: 257 | I125: 134 | J125: 251 | K125: 130 | L125: =IF(AND(ISNUMBER(J125),ISNUMBER(H125)),IF(H125>0,J125/H125,""),"") -> 0.9766537 | M125: =IF(AND(ISNUMBER(K125),ISNUMBER(I125)),IF(I125>0,K125/I125,""),"") -> 0.97014925 | N125: No answer | O125: Usable with care | P125: Recorded as a number in the camp and as a word in the towns (130 households): the format changes between groups.
A126: 125 | B126: emergency1 | C126: Original question | D126: 16 Security and whom to turn to | E126: First contact in a personal emergency | F126: The respondent | G126: All households | H126: 257 | I126: 134 | J126: 256 | K126: 111 | L126: =IF(AND(ISNUMBER(J126),ISNUMBER(H126)),IF(H126>0,J126/H126,""),"") -> 0.99610895 | M126: =IF(AND(ISNUMBER(K126),ISNUMBER(I126)),IF(I126>0,K126/I126,""),"") -> 0.82835821 | N126: Cannot be known | O126: Usable with care | P126: 256 and 111 answers. In the towns there are 23 blanks; nearly all of those households did answer the neighbouring questions.
A127: 126 | B127: emergency2 | C127: Original question | D127: 16 Security and whom to turn to | E127: Second contact in a personal emergency | F127: The respondent | G127: Only where applicable | J127: 214 | K127: 58 | L127: =IF(AND(ISNUMBER(J127),ISNUMBER(H127)),IF(H127>0,J127/H127,""),"") | M127: =IF(AND(ISNUMBER(K127),ISNUMBER(I127)),IF(I127>0,K127/I127,""),"") | N127: Not applicable | O127: Usable with care | P127: Second contact: 214 and 58 answers.
A128: 127 | B128: emergency3 | C128: Original question | D128: 16 Security and whom to turn to | E128: Third contact in a personal emergency | F128: The respondent | G128: Only where applicable | J128: 165 | K128: fewer than 10 | L128: =IF(AND(ISNUMBER(J128),ISNUMBER(H128)),IF(H128>0,J128/H128,""),"") | M128: =IF(AND(ISNUMBER(K128),ISNUMBER(I128)),IF(I128>0,K128/I128,""),"") | N128: Not applicable | O128: Usable with care | P128: Third contact: 165 camp households and fewer than ten in the towns.
A129: 128 | B129: familyintegration | C129: Original question | D129: 17 Self-rated integration | E129: Self-rated integration of the family (1 to 10) | F129: The respondent | G129: All households | H129: 257 | I129: 134 | J129: 257 | K129: 126 | L129: =IF(AND(ISNUMBER(J129),ISNUMBER(H129)),IF(H129>0,J129/H129,""),"") -> 1 | M129: =IF(AND(ISNUMBER(K129),ISNUMBER(I129)),IF(I129>0,K129/I129,""),"") -> 0.94029851 | N129: No answer | O129: Usable with care | P129: 257 and 126 answers. Self-rated integration of the family, from 1 to 10; the question does not say integration into what, and answers cluster at the ends.
A130: 129 | B130: personalintegration | C130: Original question | D130: 17 Self-rated integration | E130: Self-rated integration, personal (1 to 10) | F130: The respondent | G130: All households | H130: 257 | I130: 134 | J130: 257 | K130: 129 | L130: =IF(AND(ISNUMBER(J130),ISNUMBER(H130)),IF(H130>0,J130/H130,""),"") -> 1 | M130: =IF(AND(ISNUMBER(K130),ISNUMBER(I130)),IF(I130>0,K130/I130,""),"") -> 0.96268657 | N130: No answer | O130: Usable with care | P130: 257 and 129 answers. Self-rated integration, from 1 to 10; the question does not say integration into what. In the camp 28% answered 10; in the towns 29% answered 1.
A131: 130 | B131: decreaseinincome | C131: Original question | D131: 18 Shocks | E131: Household income fell | F131: The household | G131: All households | H131: 257 | I131: 134 | J131: 257 | K131: 133 | L131: =IF(AND(ISNUMBER(J131),ISNUMBER(H131)),IF(H131>0,J131/H131,""),"") -> 1 | M131: =IF(AND(ISNUMBER(K131),ISNUMBER(I131)),IF(I131>0,K131/I131,""),"") -> 0.99253731 | N131: No answer | O131: Usable with care | P131: Nearly complete. It refers to the whole period since arrival in Jordan.
A132: 131 | B132: causedi | C132: Original question | D132: 18 Shocks | E132: Reported cause of the fall in income | F132: The household | G132: Households whose income fell | H132: 237 | I132: 104 | J132: 233 | K132: 103 | L132: =IF(AND(ISNUMBER(J132),ISNUMBER(H132)),IF(H132>0,J132/H132,""),"") -> 0.98312236 | M132: =IF(AND(ISNUMBER(K132),ISNUMBER(I132)),IF(I132>0,K132/I132,""),"") -> 0.99038462 | N132: Not applicable | O132: Usable with care | P132: Given by nearly all households whose income fell. The cause is the household's own account.
A133: 132 | B133: theft | C133: Original question | D133: 18 Shocks | E133: The household experienced a theft | F133: The household | G133: All households | H133: 257 | I133: 134 | J133: 257 | K133: 132 | L133: =IF(AND(ISNUMBER(J133),ISNUMBER(H133)),IF(H133>0,J133/H133,""),"") -> 1 | M133: =IF(AND(ISNUMBER(K133),ISNUMBER(I133)),IF(I133>0,K133/I133,""),"") -> 0.98507463 | N133: No answer | O133: Usable with care | P133: Nearly complete. It refers to the whole period since arrival in Jordan.
A134: 133 | B134: lossemployment | C134: Original question | D134: 18 Shocks | E134: Loss of a job | F134: The household | G134: All households | H134: 257 | I134: 134 | J134: 257 | K134: 132 | L134: =IF(AND(ISNUMBER(J134),ISNUMBER(H134)),IF(H134>0,J134/H134,""),"") -> 1 | M134: =IF(AND(ISNUMBER(K134),ISNUMBER(I134)),IF(I134>0,K134/I134,""),"") -> 0.98507463 | N134: No answer | O134: Usable with care | P134: Nearly complete. It refers to the whole period since arrival in Jordan.
A135: 134 | B135: sickness | C135: Original question | D135: 18 Shocks | E135: Sickness | F135: The household | G135: All households | H135: 257 | I135: 134 | J135: 257 | K135: 133 | L135: =IF(AND(ISNUMBER(J135),ISNUMBER(H135)),IF(H135>0,J135/H135,""),"") -> 1 | M135: =IF(AND(ISNUMBER(K135),ISNUMBER(I135)),IF(I135>0,K135/I135,""),"") -> 0.99253731 | N135: No answer | O135: Usable with care | P135: Nearly complete; since arrival in Jordan. Used only as a share by group.
A136: 135 | B136: increaseworkingtime | C136: Original question | D136: 19 Responses to the fall in income | E136: Worked more hours | F136: The household | G136: All households | H136: 257 | I136: 134 | J136: 254 | K136: 129 | L136: =IF(AND(ISNUMBER(J136),ISNUMBER(H136)),IF(H136>0,J136/H136,""),"") -> 0.98832685 | M136: =IF(AND(ISNUMBER(K136),ISNUMBER(I136)),IF(I136>0,K136/I136,""),"") -> 0.96268657 | N136: No answer | O136: Usable with care | P136: Answered by nearly all households (254 to 256 and 128 to 131). It was also asked of the 49 households whose income did not fall, and it covers the whole period since arrival in Jordan.
A137: 136 | B137: morethan1job | C137: Original question | D137: 19 Responses to the fall in income | E137: Took more than one job | F137: The household | G137: All households | H137: 257 | I137: 134 | J137: 254 | K137: 128 | L137: =IF(AND(ISNUMBER(J137),ISNUMBER(H137)),IF(H137>0,J137/H137,""),"") -> 0.98832685 | M137: =IF(AND(ISNUMBER(K137),ISNUMBER(I137)),IF(I137>0,K137/I137,""),"") -> 0.95522388 | N137: No answer | O137: Usable with care | P137: Answered by nearly all households (254 to 256 and 128 to 131). It was also asked of the 49 households whose income did not fall, and it covers the whole period since arrival in Jordan.
A138: 137 | B138: childlabor | C138: Original question | D138: 19 Responses to the fall in income | E138: A child went to work | F138: The household | G138: All households | H138: 257 | I138: 134 | J138: 254 | K138: 129 | L138: =IF(AND(ISNUMBER(J138),ISNUMBER(H138)),IF(H138>0,J138/H138,""),"") -> 0.98832685 | M138: =IF(AND(ISNUMBER(K138),ISNUMBER(I138)),IF(I138>0,K138/I138,""),"") -> 0.96268657 | N138: No answer | O138: Usable with care | P138: Answered by nearly all households (254 to 256 and 128 to 131). It was also asked of the 49 households whose income did not fall, and it covers the whole period since arrival in Jordan. The number of children in the household is unknown.
A139: 138 | B139: recfoodintake | C139: Original question | D139: 19 Responses to the fall in income | E139: Ate less | F139: The household | G139: All households | H139: 257 | I139: 134 | J139: 254 | K139: 131 | L139: =IF(AND(ISNUMBER(J139),ISNUMBER(H139)),IF(H139>0,J139/H139,""),"") -> 0.98832685 | M139: =IF(AND(ISNUMBER(K139),ISNUMBER(I139)),IF(I139>0,K139/I139,""),"") -> 0.97761194 | N139: No answer | O139: Usable with care | P139: Answered by nearly all households (254 to 256 and 128 to 131). It was also asked of the 49 households whose income did not fall, and it covers the whole period since arrival in Jordan.
A140: 139 | B140: redhhcon | C140: Original question | D140: 19 Responses to the fall in income | E140: Cut other household spending | F140: The household | G140: All households | H140: 257 | I140: 134 | J140: 254 | K140: 131 | L140: =IF(AND(ISNUMBER(J140),ISNUMBER(H140)),IF(H140>0,J140/H140,""),"") -> 0.98832685 | M140: =IF(AND(ISNUMBER(K140),ISNUMBER(I140)),IF(I140>0,K140/I140,""),"") -> 0.97761194 | N140: No answer | O140: Usable with care | P140: Answered by nearly all households (254 to 256 and 128 to 131). It was also asked of the 49 households whose income did not fall, and it covers the whole period since arrival in Jordan.
... A146: 145 | B146: redexeduc | C146: Original question | D146: 19 Responses to the fall in income | E146: Cut education spending | F146: The household | G146: All households | H146: 257 | I146: 134 | J146: 256 | K146: 128 | L146: =IF(AND(ISNUMBER(J146),ISNUMBER(H146)),IF(H146>0,J146/H146,""),"") -> 0.99610895 | M146: =IF(AND(ISNUMBER(K146),ISNUMBER(I146)),IF(I146>0,K146/I146,""),"") -> 0.95522388 | N146: No answer | O146: Usable with care | P146: Answered by nearly all households (254 to 256 and 128 to 131). It was also asked of the 49 households whose income did not fall, and it covers the whole period since arrival in Jordan.
A147: 146 | B147: assistanceprovider | C147: Original question | D147: 20 Assistance received | E147: Who provided the assistance | F147: The household | G147: Only where applicable | J147: 21 | K147: 55 | L147: =IF(AND(ISNUMBER(J147),ISNUMBER(H147)),IF(H147>0,J147/H147,""),"") | M147: =IF(AND(ISNUMBER(K147),ISNUMBER(I147)),IF(I147>0,K147/I147,""),"") | N147: Cannot be known | O147: Not usable | P147: 76 answers.
A148: 147 | B148: actualresponse | C148: Original question | D148: 20 Assistance received | E148: Response obtained | F148: The household | G148: Only where applicable | J148: fewer than 10 | K148: fewer than 10 | L148: =IF(AND(ISNUMBER(J148),ISNUMBER(H148)),IF(H148>0,J148/H148,""),"") | M148: =IF(AND(ISNUMBER(K148),ISNUMBER(I148)),IF(I148>0,K148/I148,""),"") | N148: Cannot be known | O148: Not usable | P148: Fewer than ten answers per group.
...

Sheet Summary
A1: Verdicts by block
A2: Each number is computed from the Variables sheet; if a verdict is changed there, this sheet updates.
A4: Block | B4: Variables | C4: Usable | D4: Usable with care | E4: Not usable | F4: Protected
A5: 01 Identification and design | B5: =COUNTIF(Variables!$D:$D,$A5) -> 7 | C5: =COUNTIFS(Variables!$D:$D,$A5,Variables!$O:$O,C$4) -> 6 | D5: =COUNTIFS(Variables!$D:$D,$A5,Variables!$O:$O,D$4) -> 0 | E5: =COUNTIFS(Variables!$D:$D,$A5,Variables!$O:$O,E$4) -> 1 | F5: =COUNTIFS(Variables!$D:$D,$A5,Variables!$O:$O,F$4) -> 0
A6: 02 Respondent and household | B6: =COUNTIF(Variables!$D:$D,$A6) -> 6 | C6: =COUNTIFS(Variables!$D:$D,$A6,Variables!$O:$O,C$4) -> 2 | D6: =COUNTIFS(Variables!$D:$D,$A6,Variables!$O:$O,D$4) -> 3 | E6: =COUNTIFS(Variables!$D:$D,$A6,Variables!$O:$O,E$4) -> 1 | F6: =COUNTIFS(Variables!$D:$D,$A6,Variables!$O:$O,F$4) -> 0
A7: 03 Health | B7: =COUNTIF(Variables!$D:$D,$A7) -> 2 | C7: =COUNTIFS(Variables!$D:$D,$A7,Variables!$O:$O,C$4) -> 1 | D7: =COUNTIFS(Variables!$D:$D,$A7,Variables!$O:$O,D$4) -> 0 | E7: =COUNTIFS(Variables!$D:$D,$A7,Variables!$O:$O,E$4) -> 0 | F7: =COUNTIFS(Variables!$D:$D,$A7,Variables!$O:$O,F$4) -> 1
A8: 04 Origin | B8: =COUNTIF(Variables!$D:$D,$A8) -> 4 | C8: =COUNTIFS(Variables!$D:$D,$A8,Variables!$O:$O,C$4) -> 2 | D8: =COUNTIFS(Variables!$D:$D,$A8,Variables!$O:$O,D$4) -> 1 | E8: =COUNTIFS(Variables!$D:$D,$A8,Variables!$O:$O,E$4) -> 1 | F8: =COUNTIFS(Variables!$D:$D,$A8,Variables!$O:$O,F$4) -> 0
A9: 05 Arrival and trajectory | B9: =COUNTIF(Variables!$D:$D,$A9) -> 20 | C9: =COUNTIFS(Variables!$D:$D,$A9,Variables!$O:$O,C$4) -> 5 | D9: =COUNTIFS(Variables!$D:$D,$A9,Variables!$O:$O,D$4) -> 10 | E9: =COUNTIFS(Variables!$D:$D,$A9,Variables!$O:$O,E$4) -> 5 | F9: =COUNTIFS(Variables!$D:$D,$A9,Variables!$O:$O,F$4) -> 0
A10: 06 Family events | B10: =COUNTIF(Variables!$D:$D,$A10) -> 2 | C10: =COUNTIFS(Variables!$D:$D,$A10,Variables!$O:$O,C$4) -> 0 | D10: =COUNTIFS(Variables!$D:$D,$A10,Variables!$O:$O,D$4) -> 0 | E10: =COUNTIFS(Variables!$D:$D,$A10,Variables!$O:$O,E$4) -> 0 | F10: =COUNTIFS(Variables!$D:$D,$A10,Variables!$O:$O,F$4) -> 2
A11: 07 Housing | B11: =COUNTIF(Variables!$D:$D,$A11) -> 6 | C11: =COUNTIFS(Variables!$D:$D,$A11,Variables!$O:$O,C$4) -> 3 | D11: =COUNTIFS(Variables!$D:$D,$A11,Variables!$O:$O,D$4) -> 3 | E11: =COUNTIFS(Variables!$D:$D,$A11,Variables!$O:$O,E$4) -> 0 | F11: =COUNTIFS(Variables!$D:$D,$A11,Variables!$O:$O,F$4) -> 0
A12: 08 Durable goods | B12: =COUNTIF(Variables!$D:$D,$A12) -> 8 | C12: =COUNTIFS(Variables!$D:$D,$A12,Variables!$O:$O,C$4) -> 8 | D12: =COUNTIFS(Variables!$D:$D,$A12,Variables!$O:$O,D$4) -> 0 | E12: =COUNTIFS(Variables!$D:$D,$A12,Variables!$O:$O,E$4) -> 0 | F12: =COUNTIFS(Variables!$D:$D,$A12,Variables!$O:$O,F$4) -> 0
A13: 09 Leisure | B13: =COUNTIF(Variables!$D:$D,$A13) -> 4 | C13: =COUNTIFS(Variables!$D:$D,$A13,Variables!$O:$O,C$4) -> 4 | D13: =COUNTIFS(Variables!$D:$D,$A13,Variables!$O:$O,D$4) -> 0 | E13: =COUNTIFS(Variables!$D:$D,$A13,Variables!$O:$O,E$4) -> 0 | F13: =COUNTIFS(Variables!$D:$D,$A13,Variables!$O:$O,F$4) -> 0
A14: 10 Savings, debt and credit | B14: =COUNTIF(Variables!$D:$D,$A14) -> 8 | C14: =COUNTIFS(Variables!$D:$D,$A14,Variables!$O:$O,C$4) -> 8 | D14: =COUNTIFS(Variables!$D:$D,$A14,Variables!$O:$O,D$4) -> 0 | E14: =COUNTIFS(Variables!$D:$D,$A14,Variables!$O:$O,E$4) -> 0 | F14: =COUNTIFS(Variables!$D:$D,$A14,Variables!$O:$O,F$4) -> 0
A15: 11 Average day | B15: =COUNTIF(Variables!$D:$D,$A15) -> 1 | C15: =COUNTIFS(Variables!$D:$D,$A15,Variables!$O:$O,C$4) -> 0 | D15: =COUNTIFS(Variables!$D:$D,$A15,Variables!$O:$O,D$4) -> 1 | E15: =COUNTIFS(Variables!$D:$D,$A15,Variables!$O:$O,E$4) -> 0 | F15: =COUNTIFS(Variables!$D:$D,$A15,Variables!$O:$O,F$4) -> 0
A16: 12 Work | B16: =COUNTIF(Variables!$D:$D,$A16) -> 20 | C16: =COUNTIFS(Variables!$D:$D,$A16,Variables!$O:$O,C$4) -> 2 | D16: =COUNTIFS(Variables!$D:$D,$A16,Variables!$O:$O,D$4) -> 15 | E16: =COUNTIFS(Variables!$D:$D,$A16,Variables!$O:$O,E$4) -> 3 | F16: =COUNTIFS(Variables!$D:$D,$A16,Variables!$O:$O,F$4) -> 0
... A32: 36 Derived: security, self-rated integration and shocks | B32: =COUNTIF(Variables!$D:$D,$A32) -> 12 | C32: =COUNTIFS(Variables!$D:$D,$A32,Variables!$O:$O,C$4) -> 0 | D32: =COUNTIFS(Variables!$D:$D,$A32,Variables!$O:$O,D$4) -> 10 | E32: =COUNTIFS(Variables!$D:$D,$A32,Variables!$O:$O,E$4) -> 2 | F32: =COUNTIFS(Variables!$D:$D,$A32,Variables!$O:$O,F$4) -> 0
A33: Total | B33: =SUM(B5:B32) -> 275 | C33: =SUM(C5:C32) -> 50 | D33: =SUM(D5:D32) -> 145 | E33: =SUM(E5:E32) -> 77 | F33: =SUM(F5:F32) -> 3
A35: By source
A36: Source | B36: Variables | C36: Usable | D36: Usable with care | E36: Not usable | F36: Protected
A37: Original question | B37: =COUNTIF(Variables!$C:$C,$A37) -> 153 | C37: =COUNTIFS(Variables!$C:$C,$A37,Variables!$O:$O,C$36) -> 47 | D37: =COUNTIFS(Variables!$C:$C,$A37,Variables!$O:$O,D$36) -> 73 | E37: =COUNTIFS(Variables!$C:$C,$A37,Variables!$O:$O,E$36) -> 30 | F37: =COUNTIFS(Variables!$C:$C,$A37,Variables!$O:$O,F$36) -> 3
A38: Derived | B38: =COUNTIF(Variables!$C:$C,$A38) -> 122 | C38: =COUNTIFS(Variables!$C:$C,$A38,Variables!$O:$O,C$36) -> 3 | D38: =COUNTIFS(Variables!$C:$C,$A38,Variables!$O:$O,D$36) -> 72 | E38: =COUNTIFS(Variables!$C:$C,$A38,Variables!$O:$O,E$36) -> 47 | F38: =COUNTIFS(Variables!$C:$C,$A38,Variables!$O:$O,F$36) -> 0
A40: Usable: answered by nearly all households, measures a concrete fact and is consistent with the rest of the file.
A41: Usable with care: it can be used, with the caution stated in the "Why" column.
A42: Not usable: very few answers, no variation, blanks that cannot be interpreted, or a derived variable with an error.
A43: Protected: not used, to protect households.

Sheet Findings
A1: No. | B1: Topic | C1: Finding | D1: Where it comes from
A2: 1 | B2: Fieldwork | C2: Fieldwork ran from June to August 2016 (as recorded on 21 October 2026). The two documents from 2016 and 2017 in the folder say the survey was administered in June and July 2016, and the published essay says May to July. | D2: Record of 21 October 2026; Felipe Rodriguez-Preliminary Results.docx, section 2.1
A3: 2 | B3: Fieldwork | C3: The file has no interview date. In the raw sheet named Hoja3 only 16 records carry a date, all on the same day of August 2016. Ramadan ran from 6 June to 5 July 2016. | D3: Data.xlsx, sheet Hoja3 (counts only)
A4: 3 | B4: Fieldwork | C4: In the northern towns, interviews were done place by place: across the 134 interviews there are 14 consecutive runs of the same place; a random order would give between 89 and 108 (200,000 random reorderings). Irbid 52, Ramtha 38, Jerash 24, Zarqa 10 and three places with fewer than ten households. | D4: a1_values.py, section 9
A5: 4 | B5: Fieldwork | C5: In the camp, the interview order moves through the districts with less clustering: 168 runs; a random order would give between 227 and 244. | D5: a1_values.py, section 9
A6: 5 | B6: Who answered | C6: A woman answered in 21% of camp households and in 63% of those in the towns. In the towns, 65 of the 84 women who answered are married: the respondent does not always head the household. The thesis treated age and schooling as those of the household head. | D6: a1_values.py, section 2
A7: 6 | B7: Questionnaire | C7: The original questionnaire is not in the folder. The documents from 2016 and 2017 say that shocks and responses were asked for the whole period since arrival in Jordan. | D7: Felipe Rodriguez-Preliminary Results.docx, section 2.1
A8: 7 | B8: Responses to the fall in income | C8: The eleven responses were asked of all households: nearly all of the 49 whose income did not fall answered all of them. | D8: a3_logic.py, section 3
A9: 8 | B9: Security | C9: Security was recorded as a number in the camp and as a word in the towns. The 1 to 5 scale of the thesis joins the two formats. | D9: a2_derived.py, section 8
A10: 9 | B10: Opinion scales | C10: Answers cluster at the ends. In self-rated integration (personal), 28% of camp households answered 10 and 29% of those in the towns answered 1. In optimism, 27% of those in the towns answered 1. | D10: a1_values.py, section 6
A11: 10 | B11: Work | C11: Employment is that of the respondent: among men, 30% in the camp and 29% in the towns. "Some member works" comes from another question (who works): 39% and 64%. The unemployment variable of the thesis does not follow reported employment: in 54 households the respondent reports no employment and the variable shows an occupation, and the opposite case has fewer than ten households in each group. | D11: a2_derived.py, section 9; a3_logic.py, section 8
A12: 11 | B12: Income and spending | C12: Reported total spending exceeds reported income in 45% of camp households and 50% of those in the towns (231 and 119 households with both figures). Among camp households that report assistance only, in 59%. | D12: additional check on totalexj and the three income sources
A13: 12 | B13: Spending | C13: No spending item has a written zero: a blank may be zero or no answer. | D13: a3_logic.py, section 7
... A24: 23 | B24: Thesis | C24: One of the specifications in the do-file used the medical condition indicator as a matching variable (nearest-neighbour matching, the Stata command teffects nnmatch), together with schooling, savings, origin, sex of the respondent, year of arrival and agriculture. | D24: do file creating variable.do, teffects nnmatch with medicalconditionofoneofthemember

Sheet How it was done
A1: Topic | B1: Detail
A2: What was reviewed | B2: The 275 variables of data set.dta (391 households: 257 in Zaatari camp and 134 in the northern towns), the original CSV (Coded Data.csv), the two documents from 2016 and 2017, the two do-files (the Stata scripts that built the variables and ran the estimates of the thesis) and the structure of the raw sheets (Data.xlsx and Coded data.xlsx).
A3: What was not done | B3: Nothing was estimated. This table describes how each variable was measured; it does not compare outcomes between groups.
A4: Protection of households | B4: Everything was computed on the author's computer. Only counts by variable left it. No count below ten households appears in this table: it shows as "fewer than 10" and carries no percentage, and where the households missing from a category are fewer than ten the text says "nearly all". The "Answered" counts beside the "Applies" counts still show how many households did not answer each question, often fewer than ten; a question left unanswered is not a trait of the household, so that is accepted here. Since the edition of 21 October 2026 the counts by group read "not shown" for the two questions on health spending, because health is not crossed with place anywhere in the review, and for the six dollar variables, whose empty cells mark the households that arrived in 2016 (fewer than ten in each group) and would give that number next to the row for the year of arrival; the three rows derived from them (logIncomeJordan, logExpensesJordan, ExpIncratio) read "not shown" for the same reason.
A5: Answered | B5: A household counts as having answered if the cell is not empty. Percentages are computed over the households to which the question applies ("Applies" columns).
A6: Units | B6: Amounts in Jordan are in Jordanian dinars (JD) per month; amounts in Syria are in Syrian pounds. The scales keep the range of the question (1 to 5 or 1 to 10).
A7: Only where applicable | B7: Questions filled in only when there is something to report (second source of income, second contact). The number of households that answered is shown, without a percentage.
A8: Blanks | B8: The column "A blank means" records what the file alone can tell. The rule adopted after this audit (8 October 2026) is that a blank is a missing value and not a zero; the later steps of the review follow it.
A9: Original questions | B9: The 151 columns of the coded questionnaire, plus the two types of work of the father and the mother, which came from a separate file (typesofjobs.dta). The other 122 variables were built by the do-file.
A10: Verification | B10: The counts moved from the computer to this table as a text of 275 lines, with the same md5 checksum, a fingerprint of the file (0dac79f1edc7ce5c0dd2df3fb63ed8d1), on both sides. The analysis file was compared cell by cell with the original CSV.
A11: Blind replication | B11: On 9 October 2026 a separate instance of the AI assistant that prepared this review, given only written definitions and no code or results, recomputed the 275 lines from the analysis file: the text came out identical, with the same checksum. It also repeated the comparison of the two files (same result) and seventeen checks behind the findings (72 values). Two findings were corrected as a result: the range expected under a random interview order (89 to 108, not 88 to 107), and the finding on the first contact, which had given the figure for the whole sample as that of the towns.
A12: Independent review | B12: On 9 October 2026 two further instances that had produced none of the files reviewed this workbook and its chart as a reader receives them: every count matched the 275 lines and every formula was right. They found sentences where two counts side by side gave away a count below ten, a few labels and names not yet aligned with the other workbooks, and one figure (the voucher amount among camp households that report assistance only) that no script of the audit produced. The edition of 13 October 2026 reworded those sentences, aligned the names (the second group is the northern towns; the scales are self-rated integration), and added the script a6_vale_solo_asistencia.py, run on the author's computer on 13 October 2026, which confirms the figure.
... A14: What is missing | B14: The original questionnaire and the date of each interview are not in the folder. The descriptions in the "What it measures" column come from the labels in the file, the documents from 2016 and 2017 and the do-files.
